[{"id":88,"Date":1452816000000,"Player1":"Frank","Player2":"Bert","Legs1":2,"Legs2":0,"Max1":null,"Max2":null,"Finishes1":null,"Finishes2":null,"L21_1":null,"L21_2":null,"TwentyOne1":null,"TwentyOne2":null,"Year":2016,"Season":"2015-2016","Rating1":1112.2599084619,"Rating2":1102.7926870681},{"id":100,"Date":1452816000000,"Player1":"Frank","Player2":"Harry","Legs1":0,"Legs2":2,"Max1":null,"Max2":null,"Finishes1":null,"Finishes2":null,"L21_1":null,"L21_2":null,"TwentyOne1":null,"TwentyOne2":null,"Year":2016,"Season":"2015-2016","Rating1":1099.8684575783,"Rating2":1101.9759861014},{"id":109,"Date":1452816000000,"Player1":"Bas","Player2":"Frank","Legs1":2,"Legs2":1,"Max1":null,"Max2":null,"Finishes1":null,"Finishes2":null,"L21_1":null,"L21_2":null,"TwentyOne1":null,"TwentyOne2":null,"Year":2016,"Season":"2015-2016","Rating1":1101.9849761532,"Rating2":1095.8353595069},{"id":124,"Date":1452816000000,"Player1":"Youri","Player2":"Frank","Legs1":0,"Legs2":2,"Max1":null,"Max2":null,"Finishes1":null,"Finishes2":null,"L21_1":null,"L21_2":null,"TwentyOne1":null,"TwentyOne2":null,"Year":2016,"Season":"2015-2016","Rating1":1084.2194920902,"Rating2":1107.8421098145},{"id":137,"Date":1453420800000,"Player1":"Jari","Player2":"Frank","Legs1":1,"Legs2":2,"Max1":null,"Max2":null,"Finishes1":null,"Finishes2":null,"L21_1":null,"L21_2":null,"TwentyOne1":null,"TwentyOne2":null,"Year":2016,"Season":"2015-2016","Rating1":1030.8353160712,"Rating2":1110.5641218936},{"id":151,"Date":1453420800000,"Player1":"Erik H","Player2":"Frank","Legs1":0,"Legs2":2,"Max1":null,"Max2":null,"Finishes1":null,"Finishes2":null,"L21_1":null,"L21_2":null,"TwentyOne1":null,"TwentyOne2":null,"Year":2016,"Season":"2015-2016","Rating1":1143.3592114472,"Rating2":1123.3501528773},{"id":161,"Date":1453420800000,"Player1":"Frank","Player2":"JR","Legs1":2,"Legs2":1,"Max1":null,"Max2":null,"Finishes1":null,"Finishes2":null,"L21_1":null,"L21_2":null,"TwentyOne1":null,"TwentyOne2":null,"Year":2016,"Season":"2015-2016","Rating1":1125.8183227432,"Rating2":1031.6933620942},{"id":173,"Date":1453420800000,"Player1":"Frank","Player2":"Marianne","Legs1":2,"Legs2":0,"Max1":null,"Max2":null,"Finishes1":null,"Finishes2":null,"L21_1":null,"L21_2":null,"TwentyOne1":null,"TwentyOne2":null,"Year":2016,"Season":"2015-2016","Rating1":1135.6689553254,"Rating2":990.1493674178},{"id":188,"Date":1454025600000,"Player1":"Frank","Player2":"Henri","Legs1":2,"Legs2":0,"Max1":null,"Max2":null,"Finishes1":null,"Finishes2":null,"L21_1":null,"L21_2":null,"TwentyOne1":null,"TwentyOne2":null,"Year":2016,"Season":"2015-2016","Rating1":1146.0715978691,"Rating2":1032.2176413991},{"id":195,"Date":1454025600000,"Player1":"Frank","Player2":"Brandon","Legs1":2,"Legs2":0,"Max1":null,"Max2":null,"Finishes1":null,"Finishes2":null,"L21_1":null,"L21_2":null,"TwentyOne1":null,"TwentyOne2":null,"Year":2016,"Season":"2015-2016","Rating1":1156.6492497514,"Rating2":1052.7425632988},{"id":205,"Date":1454025600000,"Player1":"Youri","Player2":"Frank","Legs1":0,"Legs2":2,"Max1":null,"Max2":null,"Finishes1":null,"Finishes2":null,"L21_1":null,"L21_2":null,"TwentyOne1":null,"TwentyOne2":null,"Year":2016,"Season":"2015-2016","Rating1":1043.5484062843,"Rating2":1166.8857080506},{"id":221,"Date":1454025600000,"Player1":"Anil","Player2":"Frank","Legs1":2,"Legs2":0,"Max1":null,"Max2":null,"Finishes1":null,"Finishes2":null,"L21_1":null,"L21_2":null,"TwentyOne1":null,"TwentyOne2":null,"Year":2016,"Season":"2015-2016","Rating1":1197.0058681376,"Rating2":1155.2040550737},{"id":229,"Date":1454630400000,"Player1":"Frank","Player2":"Maik","Legs1":0,"Legs2":2,"Max1":null,"Max2":null,"Finishes1":null,"Finishes2":null,"L21_1":null,"L21_2":null,"TwentyOne1":null,"TwentyOne2":null,"Year":2016,"Season":"2015-2016","Rating1":1142.0507545398,"Rating2":1101.3676467485},{"id":246,"Date":1454630400000,"Player1":"Frank","Player2":"Bert","Legs1":1,"Legs2":2,"Max1":null,"Max2":null,"Finishes1":null,"Finishes2":null,"L21_1":null,"L21_2":null,"TwentyOne1":null,"TwentyOne2":null,"Year":2016,"Season":"2015-2016","Rating1":1138.1247295607,"Rating2":1150.2604262305},{"id":250,"Date":1454630400000,"Player1":"Ernie","Player2":"Frank","Legs1":1,"Legs2":2,"Max1":null,"Max2":null,"Finishes1":null,"Finishes2":null,"L21_1":null,"L21_2":null,"TwentyOne1":null,"TwentyOne2":null,"Year":2016,"Season":"2015-2016","Rating1":1003.2646214497,"Rating2":1139.8533545702},{"id":264,"Date":1454630400000,"Player1":"Jari","Player2":"Frank","Legs1":0,"Legs2":2,"Max1":null,"Max2":null,"Finishes1":null,"Finishes2":null,"L21_1":null,"L21_2":null,"TwentyOne1":null,"TwentyOne2":null,"Year":2016,"Season":"2015-2016","Rating1":1007.8469251041,"Rating2":1149.7663085367},{"id":276,"Date":1455235200000,"Player1":"Frank","Player2":"Joris","Legs1":1,"Legs2":2,"Max1":null,"Max2":null,"Finishes1":null,"Finishes2":null,"L21_1":null,"L21_2":null,"TwentyOne1":null,"TwentyOne2":null,"Year":2016,"Season":"2015-2016","Rating1":1144.6332332418,"Rating2":1089.0915628285},{"id":283,"Date":1455235200000,"Player1":"Frank","Player2":"Erik H","Legs1":0,"Legs2":2,"Max1":null,"Max2":null,"Finishes1":null,"Finishes2":null,"L21_1":null,"L21_2":null,"TwentyOne1":null,"TwentyOne2":null,"Year":2016,"Season":"2015-2016","Rating1":1133.5761308349,"Rating2":1210.4024821079},{"id":299,"Date":1455235200000,"Player1":"Harry","Player2":"Frank","Legs1":0,"Legs2":2,"Max1":null,"Max2":null,"Finishes1":null,"Finishes2":null,"L21_1":null,"L21_2":null,"TwentyOne1":null,"TwentyOne2":null,"Year":2016,"Season":"2015-2016","Rating1":1170.242895208,"Rating2":1146.4298748742},{"id":320,"Date":1455235200000,"Player1":"Jari","Player2":"Frank","Legs1":1,"Legs2":2,"Max1":null,"Max2":null,"Finishes1":null,"Finishes2":null,"L21_1":null,"L21_2":null,"TwentyOne1":null,"TwentyOne2":null,"Year":2016,"Season":"2015-2016","Rating1":1000.9983764042,"Rating2":1147.9800445338},{"id":328,"Date":1455840000000,"Player1":"Frank","Player2":"Elbert","Legs1":1,"Legs2":2,"Max1":null,"Max2":null,"Finishes1":null,"Finishes2":null,"L21_1":null,"L21_2":null,"TwentyOne1":null,"TwentyOne2":null,"Year":2016,"Season":"2015-2016","Rating1":1144.8355550221,"Rating2":1200.7478517974},{"id":335,"Date":1455840000000,"Player1":"Frank","Player2":"Andor","Legs1":2,"Legs2":1,"Max1":null,"Max2":null,"Finishes1":null,"Finishes2":null,"L21_1":null,"L21_2":null,"TwentyOne1":null,"TwentyOne2":null,"Year":2016,"Season":"2015-2016","Rating1":1149.4489159354,"Rating2":1175.7704079008},{"id":347,"Date":1455840000000,"Player1":"Henri","Player2":"Frank","Legs1":0,"Legs2":2,"Max1":null,"Max2":null,"Finishes1":null,"Finishes2":null,"L21_1":null,"L21_2":null,"TwentyOne1":null,"TwentyOne2":null,"Year":2016,"Season":"2015-2016","Rating1":1030.4625444182,"Rating2":1159.5843534684},{"id":376,"Date":1458259200000,"Player1":"Frank","Player2":"Ernie","Legs1":2,"Legs2":1,"Max1":null,"Max2":null,"Finishes1":null,"Finishes2":null,"L21_1":null,"L21_2":null,"TwentyOne1":null,"TwentyOne2":null,"Year":2016,"Season":"2015-2016","Rating1":1161.0733066189,"Rating2":1010.5110468495},{"id":389,"Date":1458259200000,"Player1":"Frank","Player2":"Jari","Legs1":2,"Legs2":1,"Max1":null,"Max2":null,"Finishes1":null,"Finishes2":null,"L21_1":null,"L21_2":null,"TwentyOne1":null,"TwentyOne2":null,"Year":2016,"Season":"2015-2016","Rating1":1162.3404427503,"Rating2":998.7328638686},{"id":400,"Date":1458259200000,"Player1":"Frank","Player2":"Harry","Legs1":2,"Legs2":0,"Max1":null,"Max2":null,"Finishes1":null,"Finishes2":null,"L21_1":null,"L21_2":null,"TwentyOne1":null,"TwentyOne2":null,"Year":2016,"Season":"2015-2016","Rating1":1174.9258696878,"Rating2":1183.6816402102},{"id":410,"Date":1458259200000,"Player1":"Henri","Player2":"Frank","Legs1":0,"Legs2":2,"Max1":null,"Max2":null,"Finishes1":null,"Finishes2":null,"L21_1":null,"L21_2":null,"TwentyOne1":null,"TwentyOne2":null,"Year":2016,"Season":"2015-2016","Rating1":1001.6423074661,"Rating2":1184.1440629457},{"id":417,"Date":1472774400000,"Player1":"Anil","Player2":"Frank","Legs1":2,"Legs2":0,"Max1":null,"Max2":null,"Finishes1":null,"Finishes2":null,"L21_1":null,"L21_2":null,"TwentyOne1":null,"TwentyOne2":null,"Year":2016,"Season":"2016-2017","Rating1":1283.2703982535,"Rating2":1173.6667250592},{"id":425,"Date":1472774400000,"Player1":"Andor","Player2":"Frank","Legs1":0,"Legs2":2,"Max1":null,"Max2":null,"Finishes1":null,"Finishes2":null,"L21_1":null,"L21_2":null,"TwentyOne1":null,"TwentyOne2":null,"Year":2016,"Season":"2016-2017","Rating1":1163.4238909103,"Rating2":1185.6976034207},{"id":432,"Date":1472774400000,"Player1":"Frank","Player2":"Christa","Legs1":0,"Legs2":2,"Max1":null,"Max2":null,"Finishes1":null,"Finishes2":null,"L21_1":null,"L21_2":null,"TwentyOne1":null,"TwentyOne2":null,"Year":2016,"Season":"2016-2017","Rating1":1171.7405138023,"Rating2":1085.3064691633},{"id":445,"Date":1472774400000,"Player1":"Frank","Player2":"Bert","Legs1":2,"Legs2":1,"Max1":null,"Max2":null,"Finishes1":null,"Finishes2":null,"L21_1":null,"L21_2":null,"TwentyOne1":null,"TwentyOne2":null,"Year":2016,"Season":"2016-2017","Rating1":1175.7631805995,"Rating2":1169.0303905571},{"id":454,"Date":1473379200000,"Player1":"Frank","Player2":"Harry","Legs1":1,"Legs2":2,"Max1":null,"Max2":null,"Finishes1":null,"Finishes2":null,"L21_1":null,"L21_2":null,"TwentyOne1":null,"TwentyOne2":null,"Year":2016,"Season":"2016-2017","Rating1":1172.0738864915,"Rating2":1197.4482108172},{"id":461,"Date":1473379200000,"Player1":"Frank","Player2":"Menno","Legs1":0,"Legs2":2,"Max1":null,"Max2":null,"Finishes1":null,"Finishes2":null,"L21_1":null,"L21_2":null,"TwentyOne1":null,"TwentyOne2":null,"Year":2016,"Season":"2016-2017","Rating1":1159.0711256436,"Rating2":1126.8751230705},{"id":472,"Date":1473379200000,"Player1":"Brandon","Player2":"Frank","Legs1":0,"Legs2":2,"Max1":null,"Max2":null,"Finishes1":null,"Finishes2":null,"L21_1":null,"L21_2":null,"TwentyOne1":null,"TwentyOne2":null,"Year":2016,"Season":"2016-2017","Rating1":1046.7201461483,"Rating2":1169.3204738171},{"id":481,"Date":1473379200000,"Player1":"Pietra","Player2":"Frank","Legs1":0,"Legs2":2,"Max1":null,"Max2":null,"Finishes1":null,"Finishes2":null,"L21_1":null,"L21_2":null,"TwentyOne1":null,"TwentyOne2":null,"Year":2016,"Season":"2016-2017","Rating1":1147.9503711022,"Rating2":1181.1558248218},{"id":495,"Date":1473984000000,"Player1":"Frank","Player2":"Jari","Legs1":2,"Legs2":0,"Max1":null,"Max2":null,"Finishes1":null,"Finishes2":null,"L21_1":null,"L21_2":null,"TwentyOne1":null,"TwentyOne2":null,"Year":2016,"Season":"2016-2017","Rating1":1190.0963760302,"Rating2":991.0594487916},{"id":508,"Date":1473984000000,"Player1":"Frank","Player2":"Youri","Legs1":2,"Legs2":1,"Max1":null,"Max2":null,"Finishes1":null,"Finishes2":null,"L21_1":null,"L21_2":null,"TwentyOne1":null,"TwentyOne2":null,"Year":2016,"Season":"2016-2017","Rating1":1191.1678239932,"Rating2":1015.9520699412},{"id":517,"Date":1473984000000,"Player1":"GertJ","Player2":"Frank","Legs1":2,"Legs2":0,"Max1":null,"Max2":null,"Finishes1":null,"Finishes2":null,"L21_1":null,"L21_2":null,"TwentyOne1":null,"TwentyOne2":null,"Year":2016,"Season":"2016-2017","Rating1":1292.857445815,"Rating2":1180.734770941},{"id":531,"Date":1473984000000,"Player1":"Joris","Player2":"Frank","Legs1":2,"Legs2":1,"Max1":null,"Max2":null,"Finishes1":null,"Finishes2":null,"L21_1":null,"L21_2":null,"TwentyOne1":null,"TwentyOne2":null,"Year":2016,"Season":"2016-2017","Rating1":1140.9904867918,"Rating2":1175.9671268705},{"id":542,"Date":1474588800000,"Player1":"Menno","Player2":"Frank","Legs1":0,"Legs2":2,"Max1":null,"Max2":null,"Finishes1":null,"Finishes2":null,"L21_1":null,"L21_2":null,"TwentyOne1":null,"TwentyOne2":null,"Year":2016,"Season":"2016-2017","Rating1":1113.6122098412,"Rating2":1187.0838752835},{"id":551,"Date":1474588800000,"Player1":"Youri","Player2":"Frank","Legs1":0,"Legs2":2,"Max1":null,"Max2":null,"Finishes1":null,"Finishes2":null,"L21_1":null,"L21_2":null,"TwentyOne1":null,"TwentyOne2":null,"Year":2016,"Season":"2016-2017","Rating1":991.154958083,"Rating2":1195.9289172005},{"id":558,"Date":1474588800000,"Player1":"Frank","Player2":"Joris","Legs1":1,"Legs2":2,"Max1":null,"Max2":null,"Finishes1":null,"Finishes2":null,"L21_1":null,"L21_2":null,"TwentyOne1":null,"TwentyOne2":null,"Year":2016,"Season":"2016-2017","Rating1":1191.2246551336,"Rating2":1159.8053105096},{"id":569,"Date":1474588800000,"Player1":"Frank","Player2":"Brandon","Legs1":1,"Legs2":2,"Max1":null,"Max2":null,"Finishes1":null,"Finishes2":null,"L21_1":null,"L21_2":null,"TwentyOne1":null,"TwentyOne2":null,"Year":2016,"Season":"2016-2017","Rating1":1184.9845097844,"Rating2":1066.207942713},{"id":592,"Date":1475193600000,"Player1":"Frank","Player2":"Joris","Legs1":2,"Legs2":0,"Max1":null,"Max2":null,"Finishes1":null,"Finishes2":null,"L21_1":null,"L21_2":null,"TwentyOne1":null,"TwentyOne2":null,"Year":2016,"Season":"2016-2017","Rating1":1196.4821162671,"Rating2":1144.3783241313},{"id":615,"Date":1475193600000,"Player1":"Anil","Player2":"Frank","Legs1":2,"Legs2":1,"Max1":null,"Max2":null,"Finishes1":125.0,"Finishes2":null,"L21_1":null,"L21_2":null,"TwentyOne1":null,"TwentyOne2":null,"Year":2016,"Season":"2016-2017","Rating1":1323.372829618,"Rating2":1194.6182512146},{"id":618,"Date":1475193600000,"Player1":"Johan","Player2":"Frank","Legs1":2,"Legs2":0,"Max1":null,"Max2":null,"Finishes1":null,"Finishes2":null,"L21_1":null,"L21_2":null,"TwentyOne1":null,"TwentyOne2":null,"Year":2016,"Season":"2016-2017","Rating1":1188.0299620439,"Rating2":1182.2916838691},{"id":623,"Date":1475193600000,"Player1":"Frank","Player2":"Menno","Legs1":1,"Legs2":2,"Max1":null,"Max2":null,"Finishes1":null,"Finishes2":null,"L21_1":null,"L21_2":null,"TwentyOne1":null,"TwentyOne2":null,"Year":2016,"Season":"2016-2017","Rating1":1177.0439996281,"Rating2":1115.0290013221},{"id":664,"Date":1476403200000,"Player1":"Anil","Player2":"Frank","Legs1":2,"Legs2":0,"Max1":null,"Max2":null,"Finishes1":null,"Finishes2":null,"L21_1":null,"L21_2":null,"TwentyOne1":null,"TwentyOne2":null,"Year":2016,"Season":"2016-2017","Rating1":1347.4939522022,"Rating2":1167.7786863597},{"id":678,"Date":1476403200000,"Player1":"Maik","Player2":"Frank","Legs1":2,"Legs2":0,"Max1":null,"Max2":null,"Finishes1":null,"Finishes2":null,"L21_1":null,"L21_2":null,"TwentyOne1":null,"TwentyOne2":null,"Year":2016,"Season":"2016-2017","Rating1":1238.8476588009,"Rating2":1156.8140709571},{"id":694,"Date":1476403200000,"Player1":"Frank","Player2":"Menno","Legs1":2,"Legs2":0,"Max1":null,"Max2":null,"Finishes1":null,"Finishes2":null,"L21_1":null,"L21_2":null,"TwentyOne1":null,"TwentyOne2":null,"Year":2016,"Season":"2016-2017","Rating1":1168.2765979286,"Rating2":1114.2078310584},{"id":703,"Date":1476403200000,"Player1":"Frank","Player2":"Otto","Legs1":2,"Legs2":0,"Max1":null,"Max2":null,"Finishes1":null,"Finishes2":null,"L21_1":null,"L21_2":null,"TwentyOne1":null,"TwentyOne2":null,"Year":2016,"Season":"2016-2017","Rating1":1178.7455901237,"Rating2":1068.6673909113},{"id":709,"Date":1477008000000,"Player1":"Frank","Player2":"Christa","Legs1":2,"Legs2":0,"Max1":null,"Max2":null,"Finishes1":null,"Finishes2":null,"L21_1":null,"L21_2":null,"TwentyOne1":null,"TwentyOne2":null,"Year":2016,"Season":"2016-2017","Rating1":1187.9405009433,"Rating2":1004.0598742351},{"id":713,"Date":1477008000000,"Player1":"Frank","Player2":"Marianne","Legs1":2,"Legs2":0,"Max1":null,"Max2":null,"Finishes1":null,"Finishes2":null,"L21_1":null,"L21_2":null,"TwentyOne1":null,"TwentyOne2":null,"Year":2016,"Season":"2016-2017","Rating1":1196.7717764974,"Rating2":991.168724446},{"id":730,"Date":1477008000000,"Player1":"Otto","Player2":"Frank","Legs1":0,"Legs2":2,"Max1":null,"Max2":null,"Finishes1":null,"Finishes2":null,"L21_1":null,"L21_2":null,"TwentyOne1":null,"TwentyOne2":null,"Year":2016,"Season":"2016-2017","Rating1":1056.8119538816,"Rating2":1206.5495507672},{"id":737,"Date":1477008000000,"Player1":"Andor","Player2":"Frank","Legs1":2,"Legs2":0,"Max1":null,"Max2":null,"Finishes1":null,"Finishes2":null,"L21_1":null,"L21_2":null,"TwentyOne1":null,"TwentyOne2":null,"Year":2016,"Season":"2016-2017","Rating1":1221.0918165322,"Rating2":1194.5942254394},{"id":742,"Date":1477612800000,"Player1":"Frank","Player2":"Henri","Legs1":0,"Legs2":2,"Max1":null,"Max2":null,"Finishes1":null,"Finishes2":null,"L21_1":null,"L21_2":null,"TwentyOne1":null,"TwentyOne2":null,"Year":2016,"Season":"2016-2017","Rating1":1179.3188802263,"Rating2":1015.2753452131},{"id":756,"Date":1477612800000,"Player1":"Frank","Player2":"EdG","Legs1":2,"Legs2":1,"Max1":null,"Max2":null,"Finishes1":null,"Finishes2":null,"L21_1":null,"L21_2":null,"TwentyOne1":null,"TwentyOne2":null,"Year":2016,"Season":"2016-2017","Rating1":1180.7090057883,"Rating2":1024.3486875298},{"id":769,"Date":1477612800000,"Player1":"Otto","Player2":"Frank","Legs1":2,"Legs2":0,"Max1":null,"Max2":null,"Finishes1":null,"Finishes2":null,"L21_1":null,"L21_2":null,"TwentyOne1":null,"TwentyOne2":null,"Year":2016,"Season":"2016-2017","Rating1":1065.4722979427,"Rating2":1166.4990465263},{"id":783,"Date":1477612800000,"Player1":"Maik","Player2":"Frank","Legs1":2,"Legs2":0,"Max1":null,"Max2":null,"Finishes1":null,"Finishes2":null,"L21_1":null,"L21_2":null,"TwentyOne1":null,"TwentyOne2":null,"Year":2016,"Season":"2016-2017","Rating1":1256.786560207,"Rating2":1155.8686823795},{"id":831,"Date":1478822400000,"Player1":"Andor","Player2":"Frank","Legs1":2,"Legs2":0,"Max1":null,"Max2":null,"Finishes1":null,"Finishes2":null,"L21_1":null,"L21_2":null,"TwentyOne1":null,"TwentyOne2":null,"Year":2016,"Season":"2016-2017","Rating1":1217.7894068403,"Rating2":1144.7443456593},{"id":832,"Date":1478822400000,"Player1":"Pietra","Player2":"Frank","Legs1":0,"Legs2":2,"Max1":null,"Max2":null,"Finishes1":null,"Finishes2":null,"L21_1":null,"L21_2":null,"TwentyOne1":null,"TwentyOne2":null,"Year":2016,"Season":"2016-2017","Rating1":1088.8289786018,"Rating2":1155.9737077397},{"id":858,"Date":1478822400000,"Player1":"Frank","Player2":"Youri","Legs1":2,"Legs2":0,"Max1":null,"Max2":null,"Finishes1":null,"Finishes2":null,"L21_1":null,"L21_2":null,"TwentyOne1":null,"TwentyOne2":null,"Year":2016,"Season":"2016-2017","Rating1":1165.3621868976,"Rating2":992.9050882673},{"id":862,"Date":1478822400000,"Player1":"Frank","Player2":"JR","Legs1":2,"Legs2":1,"Max1":null,"Max2":null,"Finishes1":null,"Finishes2":null,"L21_1":null,"L21_2":null,"TwentyOne1":null,"TwentyOne2":null,"Year":2016,"Season":"2016-2017","Rating1":1166.5591975956,"Rating2":998.802989302},{"id":920,"Date":1480032000000,"Player1":"Elbert","Player2":"Frank","Legs1":0,"Legs2":2,"Max1":null,"Max2":null,"Finishes1":null,"Finishes2":null,"L21_1":null,"L21_2":null,"TwentyOne1":null,"TwentyOne2":null,"Year":2016,"Season":"2016-2017","Rating1":1340.9285977031,"Rating2":1181.7539909026},{"id":924,"Date":1480032000000,"Player1":"Christa","Player2":"Frank","Legs1":0,"Legs2":2,"Max1":null,"Max2":null,"Finishes1":null,"Finishes2":null,"L21_1":null,"L21_2":null,"TwentyOne1":null,"TwentyOne2":null,"Year":2016,"Season":"2016-2017","Rating1":991.0691051684,"Rating2":1190.6848857342},{"id":934,"Date":1480032000000,"Player1":"Frank","Player2":"GertJ","Legs1":0,"Legs2":2,"Max1":null,"Max2":null,"Finishes1":null,"Finishes2":null,"L21_1":null,"L21_2":null,"TwentyOne1":null,"TwentyOne2":null,"Year":2016,"Season":"2016-2017","Rating1":1180.4408184157,"Rating2":1303.343047495},{"id":947,"Date":1480032000000,"Player1":"Frank","Player2":"Maik","Legs1":0,"Legs2":2,"Max1":null,"Max2":null,"Finishes1":null,"Finishes2":null,"L21_1":null,"L21_2":null,"TwentyOne1":null,"TwentyOne2":null,"Year":2016,"Season":"2016-2017","Rating1":1169.9979253998,"Rating2":1281.5606669707},{"id":1004,"Date":1481241600000,"Player1":"Frank","Player2":"Henri","Legs1":2,"Legs2":0,"Max1":null,"Max2":null,"Finishes1":null,"Finishes2":null,"L21_1":null,"L21_2":null,"TwentyOne1":null,"TwentyOne2":null,"Year":2016,"Season":"2016-2017","Rating1":1179.4142696511,"Rating2":1008.5943198188},{"id":1005,"Date":1481241600000,"Player1":"Frank","Player2":"Youri","Legs1":2,"Legs2":1,"Max1":null,"Max2":null,"Finishes1":null,"Finishes2":null,"L21_1":null,"L21_2":null,"TwentyOne1":null,"TwentyOne2":null,"Year":2016,"Season":"2016-2017","Rating1":1180.4251896415,"Rating2":1001.5986742337},{"id":1020,"Date":1481241600000,"Player1":"JR","Player2":"Frank","Legs1":0,"Legs2":2,"Max1":null,"Max2":null,"Finishes1":null,"Finishes2":null,"L21_1":null,"L21_2":null,"TwentyOne1":null,"TwentyOne2":null,"Year":2016,"Season":"2016-2017","Rating1":991.0476481753,"Rating2":1189.3775414662},{"id":1031,"Date":1481241600000,"Player1":"Pietra","Player2":"Frank","Legs1":1,"Legs2":2,"Max1":null,"Max2":null,"Finishes1":null,"Finishes2":null,"L21_1":null,"L21_2":null,"TwentyOne1":null,"TwentyOne2":null,"Year":2016,"Season":"2016-2017","Rating1":1081.9883281741,"Rating2":1191.574689838},{"id":1037,"Date":1482451200000,"Player1":"Frank","Player2":"Otto","Legs1":1,"Legs2":2,"Max1":null,"Max2":null,"Finishes1":null,"Finishes2":null,"L21_1":null,"L21_2":null,"TwentyOne1":null,"TwentyOne2":null,"Year":2016,"Season":"2016-2017","Rating1":1184.9289920869,"Rating2":1042.4614525418},{"id":1052,"Date":1482451200000,"Player1":"Jari","Player2":"Frank","Legs1":1,"Legs2":2,"Max1":null,"Max2":null,"Finishes1":null,"Finishes2":null,"L21_1":null,"L21_2":null,"TwentyOne1":null,"TwentyOne2":null,"Year":2016,"Season":"2016-2017","Rating1":1043.0623840914,"Rating2":1186.5392166664},{"id":1060,"Date":1482451200000,"Player1":"Frank","Player2":"Ernie","Legs1":2,"Legs2":1,"Max1":null,"Max2":null,"Finishes1":null,"Finishes2":null,"L21_1":null,"L21_2":null,"TwentyOne1":null,"TwentyOne2":null,"Year":2016,"Season":"2016-2017","Rating1":1187.3930161388,"Rating2":999.1462005276},{"id":1068,"Date":1482451200000,"Player1":"Anil","Player2":"Frank","Legs1":0,"Legs2":2,"Max1":null,"Max2":null,"Finishes1":null,"Finishes2":null,"L21_1":null,"L21_2":null,"TwentyOne1":null,"TwentyOne2":null,"Year":2016,"Season":"2016-2017","Rating1":1459.6244560328,"Rating2":1204.1140164039},{"id":1074,"Date":1483660800000,"Player1":"Frank","Player2":"Youri","Legs1":0,"Legs2":2,"Max1":null,"Max2":null,"Finishes1":null,"Finishes2":null,"L21_1":null,"L21_2":null,"TwentyOne1":null,"TwentyOne2":null,"Year":2017,"Season":"2016-2017","Rating1":1188.9009318992,"Rating2":1028.622438584},{"id":1096,"Date":1483660800000,"Player1":"Frank","Player2":"Joris","Legs1":1,"Legs2":2,"Max1":null,"Max2":null,"Finishes1":null,"Finishes2":null,"L21_1":null,"L21_2":null,"TwentyOne1":null,"TwentyOne2":null,"Year":2017,"Season":"2016-2017","Rating1":1185.2768227954,"Rating2":1214.2984765593},{"id":1103,"Date":1483660800000,"Player1":"Maik","Player2":"Frank","Legs1":2,"Legs2":0,"Max1":null,"Max2":null,"Finishes1":null,"Finishes2":null,"L21_1":null,"L21_2":null,"TwentyOne1":null,"TwentyOne2":null,"Year":2017,"Season":"2016-2017","Rating1":1292.6890918735,"Rating2":1174.9424765347},{"id":1113,"Date":1483660800000,"Player1":"Otto","Player2":"Frank","Legs1":1,"Legs2":2,"Max1":null,"Max2":null,"Finishes1":null,"Finishes2":null,"L21_1":null,"L21_2":null,"TwentyOne1":null,"TwentyOne2":null,"Year":2017,"Season":"2016-2017","Rating1":1019.0312856893,"Rating2":1176.3168661348},{"id":1137,"Date":1484265600000,"Player1":"GertJ","Player2":"Frank","Legs1":1,"Legs2":2,"Max1":null,"Max2":null,"Finishes1":null,"Finishes2":null,"L21_1":null,"L21_2":null,"TwentyOne1":null,"TwentyOne2":null,"Year":2017,"Season":"2016-2017","Rating1":1253.4944202212,"Rating2":1181.7365902828},{"id":1149,"Date":1484265600000,"Player1":"Frank","Player2":"Paplip","Legs1":1,"Legs2":2,"Max1":null,"Max2":null,"Finishes1":null,"Finishes2":null,"L21_1":null,"L21_2":null,"TwentyOne1":null,"TwentyOne2":null,"Year":2017,"Season":"2016-2017","Rating1":1179.8084552282,"Rating2":1304.8519109381},{"id":1153,"Date":1484265600000,"Player1":"JR","Player2":"Frank","Legs1":0,"Legs2":2,"Max1":null,"Max2":null,"Finishes1":null,"Finishes2":null,"L21_1":null,"L21_2":null,"TwentyOne1":null,"TwentyOne2":null,"Year":2017,"Season":"2016-2017","Rating1":1029.0532259764,"Rating2":1189.4036979022},{"id":1154,"Date":1484265600000,"Player1":"Frank","Player2":"Johan","Legs1":2,"Legs2":1,"Max1":null,"Max2":null,"Finishes1":null,"Finishes2":null,"L21_1":null,"L21_2":null,"TwentyOne1":null,"TwentyOne2":null,"Year":2017,"Season":"2016-2017","Rating1":1194.4974147741,"Rating2":1247.8189234531},{"id":1157,"Date":1484870400000,"Player1":"Frank","Player2":"Pietra","Legs1":2,"Legs2":0,"Max1":null,"Max2":null,"Finishes1":null,"Finishes2":null,"L21_1":null,"L21_2":null,"TwentyOne1":null,"TwentyOne2":null,"Year":2017,"Season":"2016-2017","Rating1":1204.6987555048,"Rating2":1079.3523642514},{"id":1165,"Date":1484870400000,"Player1":"Frank","Player2":"Maik","Legs1":2,"Legs2":1,"Max1":null,"Max2":null,"Finishes1":null,"Finishes2":null,"L21_1":null,"L21_2":null,"TwentyOne1":null,"TwentyOne2":null,"Year":2017,"Season":"2016-2017","Rating1":1210.3200094158,"Rating2":1293.5352626553},{"id":1181,"Date":1484870400000,"Player1":"Paplip","Player2":"Frank","Legs1":1,"Legs2":2,"Max1":null,"Max2":null,"Finishes1":null,"Finishes2":null,"L21_1":null,"L21_2":null,"TwentyOne1":null,"TwentyOne2":null,"Year":2017,"Season":"2016-2017","Rating1":1325.1587129966,"Rating2":1216.3871604467},{"id":1195,"Date":1484870400000,"Player1":"JR","Player2":"Frank","Legs1":1,"Legs2":2,"Max1":null,"Max2":null,"Finishes1":null,"Finishes2":null,"L21_1":null,"L21_2":null,"TwentyOne1":null,"TwentyOne2":null,"Year":2017,"Season":"2016-2017","Rating1":1031.0466642911,"Rating2":1217.2745354351},{"id":1225,"Date":1485475200000,"Player1":"Andor","Player2":"Frank","Legs1":0,"Legs2":2,"Max1":null,"Max2":null,"Finishes1":null,"Finishes2":null,"L21_1":null,"L21_2":null,"TwentyOne1":null,"TwentyOne2":null,"Year":2017,"Season":"2016-2017","Rating1":1283.0700529583,"Rating2":1230.6356393786},{"id":1226,"Date":1485475200000,"Player1":"Frank","Player2":"Anil","Legs1":2,"Legs2":1,"Max1":null,"Max2":null,"Finishes1":null,"Finishes2":null,"L21_1":null,"L21_2":null,"TwentyOne1":null,"TwentyOne2":null,"Year":2017,"Season":"2016-2017","Rating1":1238.8898853992,"Rating2":1479.9038973901},{"id":1227,"Date":1485475200000,"Player1":"Otto","Player2":"Frank","Legs1":0,"Legs2":2,"Max1":null,"Max2":null,"Finishes1":null,"Finishes2":null,"L21_1":null,"L21_2":null,"TwentyOne1":null,"TwentyOne2":null,"Year":2017,"Season":"2016-2017","Rating1":1007.5386971358,"Rating2":1247.1645989916},{"id":1228,"Date":1485475200000,"Player1":"Frank","Player2":"Henri","Legs1":2,"Legs2":1,"Max1":null,"Max2":null,"Finishes1":null,"Finishes2":null,"L21_1":null,"L21_2":null,"TwentyOne1":null,"TwentyOne2":null,"Year":2017,"Season":"2016-2017","Rating1":1247.2157437168,"Rating2":1009.615947342},{"id":1236,"Date":1486080000000,"Player1":"Frank","Player2":"EdG","Legs1":2,"Legs2":0,"Max1":null,"Max2":null,"Finishes1":null,"Finishes2":null,"L21_1":null,"L21_2":null,"TwentyOne1":null,"TwentyOne2":null,"Year":2017,"Season":"2016-2017","Rating1":1255.5809547572,"Rating2":1021.5584354792},{"id":1244,"Date":1486080000000,"Player1":"Frank","Player2":"Bert","Legs1":2,"Legs2":0,"Max1":null,"Max2":null,"Finishes1":null,"Finishes2":null,"L21_1":null,"L21_2":null,"TwentyOne1":null,"TwentyOne2":null,"Year":2017,"Season":"2016-2017","Rating1":1269.3755604481,"Rating2":1346.4899503797},{"id":1252,"Date":1486080000000,"Player1":"Ernie","Player2":"Frank","Legs1":2,"Legs2":1,"Max1":null,"Max2":null,"Finishes1":null,"Finishes2":null,"L21_1":null,"L21_2":null,"TwentyOne1":null,"TwentyOne2":null,"Year":2017,"Season":"2016-2017","Rating1":1022.9807610924,"Rating2":1261.1654319979},{"id":1264,"Date":1486080000000,"Player1":"GertJ","Player2":"Frank","Legs1":0,"Legs2":2,"Max1":null,"Max2":null,"Finishes1":null,"Finishes2":null,"L21_1":null,"L21_2":null,"TwentyOne1":null,"TwentyOne2":null,"Year":2017,"Season":"2016-2017","Rating1":1276.4361906106,"Rating2":1273.6443981749},{"id":1309,"Date":1487289600000,"Player1":"EdG","Player2":"Frank","Legs1":0,"Legs2":2,"Max1":null,"Max2":null,"Finishes1":null,"Finishes2":null,"L21_1":null,"L21_2":null,"TwentyOne1":null,"TwentyOne2":null,"Year":2017,"Season":"2016-2017","Rating1":1037.0830048884,"Rating2":1281.836716739},{"id":1314,"Date":1487289600000,"Player1":"Frank","Player2":"GertJ","Legs1":2,"Legs2":0,"Max1":null,"Max2":null,"Finishes1":null,"Finishes2":null,"L21_1":null,"L21_2":null,"TwentyOne1":null,"TwentyOne2":null,"Year":2017,"Season":"2016-2017","Rating1":1293.7021038825,"Rating2":1262.1761198384},{"id":1315,"Date":1487289600000,"Player1":"Frank","Player2":"Henri","Legs1":2,"Legs2":1,"Max1":null,"Max2":null,"Finishes1":null,"Finishes2":null,"L21_1":null,"L21_2":null,"TwentyOne1":null,"TwentyOne2":null,"Year":2017,"Season":"2016-2017","Rating1":1293.0765252081,"Rating2":1011.8886235796},{"id":1319,"Date":1487289600000,"Player1":"Johan","Player2":"Frank","Legs1":2,"Legs2":1,"Max1":null,"Max2":null,"Finishes1":null,"Finishes2":null,"L21_1":null,"L21_2":null,"TwentyOne1":null,"TwentyOne2":null,"Year":2017,"Season":"2016-2017","Rating1":1230.5882971654,"Rating2":1287.9118790429},{"id":1334,"Date":1487894400000,"Player1":"Christa","Player2":"Frank","Legs1":1,"Legs2":2,"Max1":null,"Max2":null,"Finishes1":null,"Finishes2":null,"L21_1":null,"L21_2":null,"TwentyOne1":null,"TwentyOne2":null,"Year":2017,"Season":"2016-2017","Rating1":1017.2687368161,"Rating2":1287.4540495212},{"id":1348,"Date":1487894400000,"Player1":"EdG","Player2":"Frank","Legs1":0,"Legs2":2,"Max1":null,"Max2":null,"Finishes1":null,"Finishes2":null,"L21_1":null,"L21_2":null,"TwentyOne1":null,"TwentyOne2":null,"Year":2017,"Season":"2016-2017","Rating1":1028.1165304989,"Rating2":1295.2910060513},{"id":1361,"Date":1487894400000,"Player1":"Frank","Player2":"Andor","Legs1":2,"Legs2":1,"Max1":null,"Max2":null,"Finishes1":null,"Finishes2":null,"L21_1":null,"L21_2":null,"TwentyOne1":null,"TwentyOne2":null,"Year":2017,"Season":"2016-2017","Rating1":1299.4686180339,"Rating2":1301.3989323917},{"id":1368,"Date":1487894400000,"Player1":"Frank","Player2":"Youri","Legs1":2,"Legs2":0,"Max1":null,"Max2":null,"Finishes1":null,"Finishes2":null,"L21_1":null,"L21_2":null,"TwentyOne1":null,"TwentyOne2":null,"Year":2017,"Season":"2016-2017","Rating1":1306.9987439504,"Rating2":1020.028059734},{"id":1443,"Date":1489708800000,"Player1":"Frank","Player2":"JR","Legs1":0,"Legs2":2,"Max1":null,"Max2":null,"Finishes1":null,"Finishes2":null,"L21_1":null,"L21_2":null,"TwentyOne1":null,"TwentyOne2":null,"Year":2017,"Season":"2016-2017","Rating1":1290.017053167,"Rating2":1016.9816907834},{"id":1452,"Date":1489708800000,"Player1":"Frank","Player2":"Elbert","Legs1":0,"Legs2":2,"Max1":null,"Max2":null,"Finishes1":null,"Finishes2":null,"L21_1":null,"L21_2":null,"TwentyOne1":null,"TwentyOne2":null,"Year":2017,"Season":"2016-2017","Rating1":1279.788142332,"Rating2":1403.5570818985},{"id":1460,"Date":1489708800000,"Player1":"Andor","Player2":"Frank","Legs1":1,"Legs2":2,"Max1":null,"Max2":null,"Finishes1":null,"Finishes2":null,"L21_1":null,"L21_2":null,"TwentyOne1":null,"TwentyOne2":null,"Year":2017,"Season":"2016-2017","Rating1":1312.164899391,"Rating2":1284.4267714548},{"id":1468,"Date":1489708800000,"Player1":"Otto","Player2":"Frank","Legs1":0,"Legs2":2,"Max1":null,"Max2":null,"Finishes1":null,"Finishes2":null,"L21_1":null,"L21_2":null,"TwentyOne1":null,"TwentyOne2":null,"Year":2017,"Season":"2016-2017","Rating1":1002.7723810259,"Rating2":1291.923514223},{"id":1598,"Date":1504224000000,"Player1":"Maik","Player2":"Frank","Legs1":2,"Legs2":0,"Max1":null,"Max2":null,"Finishes1":null,"Finishes2":null,"L21_1":null,"L21_2":null,"TwentyOne1":null,"TwentyOne2":null,"Year":2017,"Season":"2017-2018","Rating1":1347.5954134237,"Rating2":1280.6898915705},{"id":1607,"Date":1504224000000,"Player1":"GertJ","Player2":"Frank","Legs1":1,"Legs2":2,"Max1":null,"Max2":null,"Finishes1":null,"Finishes2":null,"L21_1":null,"L21_2":null,"TwentyOne1":null,"TwentyOne2":null,"Year":2017,"Season":"2017-2018","Rating1":1323.1975667123,"Rating2":1285.5058811266},{"id":1610,"Date":1504224000000,"Player1":"Frank","Player2":"Christa","Legs1":2,"Legs2":0,"Max1":null,"Max2":null,"Finishes1":null,"Finishes2":null,"L21_1":null,"L21_2":null,"TwentyOne1":null,"TwentyOne2":null,"Year":2017,"Season":"2017-2018","Rating1":1293.1930209711,"Rating2":1016.4064762243},{"id":1619,"Date":1504224000000,"Player1":"Frank","Player2":"Elbert","Legs1":0,"Legs2":2,"Max1":null,"Max2":null,"Finishes1":null,"Finishes2":null,"L21_1":null,"L21_2":null,"TwentyOne1":null,"TwentyOne2":null,"Year":2017,"Season":"2017-2018","Rating1":1283.320828283,"Rating2":1427.5941252751},{"id":1627,"Date":1504828800000,"Player1":"Henri","Player2":"Frank","Legs1":1,"Legs2":2,"Max1":null,"Max2":null,"Finishes1":null,"Finishes2":null,"L21_1":null,"L21_2":null,"TwentyOne1":null,"TwentyOne2":null,"Year":2017,"Season":"2017-2018","Rating1":1034.4658130995,"Rating2":1283.196126955},{"id":1634,"Date":1504828800000,"Player1":"Youri","Player2":"Frank","Legs1":1,"Legs2":2,"Max1":null,"Max2":null,"Finishes1":null,"Finishes2":null,"L21_1":null,"L21_2":null,"TwentyOne1":null,"TwentyOne2":null,"Year":2017,"Season":"2017-2018","Rating1":1033.3764101005,"Rating2":1283.0565142745},{"id":1645,"Date":1504828800000,"Player1":"Menno","Player2":"Frank","Legs1":0,"Legs2":2,"Max1":null,"Max2":null,"Finishes1":null,"Finishes2":null,"L21_1":null,"L21_2":null,"TwentyOne1":null,"TwentyOne2":null,"Year":2017,"Season":"2017-2018","Rating1":1235.9582158114,"Rating2":1294.4402888259},{"id":1651,"Date":1504828800000,"Player1":"Frank","Player2":"Johan","Legs1":0,"Legs2":2,"Max1":null,"Max2":null,"Finishes1":null,"Finishes2":null,"L21_1":null,"L21_2":null,"TwentyOne1":null,"TwentyOne2":null,"Year":2017,"Season":"2017-2018","Rating1":1281.7314851893,"Rating2":1266.0573250523},{"id":1658,"Date":1505433600000,"Player1":"Frank","Player2":"GertJ","Legs1":2,"Legs2":0,"Max1":null,"Max2":null,"Finishes1":null,"Finishes2":null,"L21_1":null,"L21_2":null,"TwentyOne1":null,"TwentyOne2":null,"Year":2017,"Season":"2017-2018","Rating1":1294.9228507345,"Rating2":1337.755260326},{"id":1671,"Date":1505433600000,"Player1":"Otto","Player2":"Frank","Legs1":0,"Legs2":2,"Max1":null,"Max2":null,"Finishes1":null,"Finishes2":null,"L21_1":null,"L21_2":null,"TwentyOne1":null,"TwentyOne2":null,"Year":2017,"Season":"2017-2018","Rating1":1009.6129055683,"Rating2":1302.3646501155},{"id":1681,"Date":1505433600000,"Player1":"Elbert","Player2":"Frank","Legs1":1,"Legs2":2,"Max1":null,"Max2":null,"Finishes1":null,"Finishes2":null,"L21_1":null,"L21_2":null,"TwentyOne1":null,"TwentyOne2":null,"Year":2017,"Season":"2017-2018","Rating1":1430.9463862373,"Rating2":1308.6651625686},{"id":1684,"Date":1505433600000,"Player1":"Frank","Player2":"Maik","Legs1":2,"Legs2":1,"Max1":null,"Max2":null,"Finishes1":null,"Finishes2":null,"L21_1":null,"L21_2":null,"TwentyOne1":null,"TwentyOne2":null,"Year":2017,"Season":"2017-2018","Rating1":1312.5575821175,"Rating2":1298.5430299489},{"id":1687,"Date":1506038400000,"Player1":"GertJ","Player2":"Frank","Legs1":2,"Legs2":0,"Max1":null,"Max2":null,"Finishes1":null,"Finishes2":null,"L21_1":null,"L21_2":null,"TwentyOne1":null,"TwentyOne2":null,"Year":2017,"Season":"2017-2018","Rating1":1354.3993986976,"Rating2":1301.0816487838},{"id":1695,"Date":1506038400000,"Player1":"Frank","Player2":"Ernie","Legs1":2,"Legs2":0,"Max1":null,"Max2":null,"Finishes1":null,"Finishes2":null,"L21_1":null,"L21_2":null,"TwentyOne1":null,"TwentyOne2":null,"Year":2017,"Season":"2017-2018","Rating1":1308.1904948315,"Rating2":993.2846337746},{"id":1703,"Date":1506038400000,"Player1":"Frank","Player2":"Maik","Legs1":0,"Legs2":2,"Max1":null,"Max2":null,"Finishes1":null,"Finishes2":null,"L21_1":null,"L21_2":null,"TwentyOne1":null,"TwentyOne2":null,"Year":2017,"Season":"2017-2018","Rating1":1295.8671791264,"Rating2":1301.7873814535},{"id":1710,"Date":1506038400000,"Player1":"Marianne","Player2":"Frank","Legs1":0,"Legs2":2,"Max1":null,"Max2":null,"Finishes1":null,"Finishes2":null,"L21_1":null,"L21_2":null,"TwentyOne1":null,"TwentyOne2":null,"Year":2017,"Season":"2017-2018","Rating1":992.8215342771,"Rating2":1303.0456448493},{"id":1720,"Date":1506643200000,"Player1":"Bas","Player2":"Frank","Legs1":2,"Legs2":0,"Max1":null,"Max2":null,"Finishes1":null,"Finishes2":null,"L21_1":null,"L21_2":null,"TwentyOne1":null,"TwentyOne2":null,"Year":2017,"Season":"2017-2018","Rating1":1306.3099348154,"Rating2":1290.892141954},{"id":1730,"Date":1506643200000,"Player1":"Johan","Player2":"Frank","Legs1":2,"Legs2":0,"Max1":null,"Max2":null,"Finishes1":null,"Finishes2":null,"L21_1":null,"L21_2":null,"TwentyOne1":null,"TwentyOne2":null,"Year":2017,"Season":"2017-2018","Rating1":1284.4358373891,"Rating2":1278.56789222},{"id":1741,"Date":1506643200000,"Player1":"Youri","Player2":"Frank","Legs1":1,"Legs2":2,"Max1":null,"Max2":null,"Finishes1":null,"Finishes2":109.0,"L21_1":null,"L21_2":null,"TwentyOne1":null,"TwentyOne2":null,"Year":2017,"Season":"2017-2018","Rating1":1039.4376311606,"Rating2":1278.5943194463},{"id":1745,"Date":1506643200000,"Player1":"Frank","Player2":"Andor","Legs1":0,"Legs2":2,"Max1":null,"Max2":null,"Finishes1":null,"Finishes2":null,"L21_1":null,"L21_2":null,"TwentyOne1":null,"TwentyOne2":null,"Year":2017,"Season":"2017-2018","Rating1":1268.3559985822,"Rating2":1391.5867936762},{"id":1754,"Date":1507248000000,"Player1":"Johan","Player2":"Frank","Legs1":0,"Legs2":2,"Max1":null,"Max2":null,"Finishes1":null,"Finishes2":null,"L21_1":null,"L21_2":null,"TwentyOne1":null,"TwentyOne2":null,"Year":2017,"Season":"2017-2018","Rating1":1284.7601414973,"Rating2":1280.8548479183},{"id":1763,"Date":1507248000000,"Player1":"GertJ","Player2":"Frank","Legs1":0,"Legs2":2,"Max1":null,"Max2":null,"Finishes1":null,"Finishes2":null,"L21_1":null,"L21_2":null,"TwentyOne1":null,"TwentyOne2":null,"Year":2017,"Season":"2017-2018","Rating1":1314.0715044974,"Rating2":1293.6482543948},{"id":1766,"Date":1507248000000,"Player1":"Frank","Player2":"Youri","Legs1":2,"Legs2":1,"Max1":null,"Max2":null,"Finishes1":null,"Finishes2":null,"L21_1":null,"L21_2":null,"TwentyOne1":null,"TwentyOne2":null,"Year":2017,"Season":"2017-2018","Rating1":1293.3290828704,"Rating2":1032.1353936205},{"id":1777,"Date":1507248000000,"Player1":"Frank","Player2":"Menno","Legs1":0,"Legs2":2,"Max1":null,"Max2":null,"Finishes1":null,"Finishes2":null,"L21_1":null,"L21_2":null,"TwentyOne1":null,"TwentyOne2":null,"Year":2017,"Season":"2017-2018","Rating1":1280.6474069045,"Rating2":1266.495135706},{"id":1781,"Date":1507852800000,"Player1":"Frank","Player2":"Henri","Legs1":2,"Legs2":1,"Max1":null,"Max2":null,"Finishes1":null,"Finishes2":null,"L21_1":null,"L21_2":null,"TwentyOne1":null,"TwentyOne2":null,"Year":2017,"Season":"2017-2018","Rating1":1281.9222811805,"Rating2":1118.7717484806},{"id":1783,"Date":1507852800000,"Player1":"John","Player2":"Frank","Legs1":1,"Legs2":2,"Max1":null,"Max2":null,"Finishes1":null,"Finishes2":null,"L21_1":null,"L21_2":null,"TwentyOne1":null,"TwentyOne2":null,"Year":2017,"Season":"2017-2018","Rating1":1059.2280007575,"Rating2":1282.2074115289},{"id":1789,"Date":1507852800000,"Player1":"Jari","Player2":"Frank","Legs1":2,"Legs2":0,"Max1":null,"Max2":null,"Finishes1":null,"Finishes2":null,"L21_1":null,"L21_2":null,"TwentyOne1":null,"TwentyOne2":null,"Year":2017,"Season":"2017-2018","Rating1":1088.0208022769,"Rating2":1266.6920640435},{"id":1801,"Date":1507852800000,"Player1":"Frank","Player2":"Marianne","Legs1":2,"Legs2":1,"Max1":null,"Max2":null,"Finishes1":null,"Finishes2":null,"L21_1":null,"L21_2":null,"TwentyOne1":null,"TwentyOne2":null,"Year":2017,"Season":"2017-2018","Rating1":1266.3000205084,"Rating2":1000.3920435351},{"id":1815,"Date":1508457600000,"Player1":"Frank","Player2":"Marianne","Legs1":2,"Legs2":0,"Max1":null,"Max2":null,"Finishes1":null,"Finishes2":null,"L21_1":null,"L21_2":null,"TwentyOne1":null,"TwentyOne2":null,"Year":2017,"Season":"2017-2018","Rating1":1273.9347663284,"Rating2":993.7627369693},{"id":1818,"Date":1508457600000,"Player1":"Frank","Player2":"Menno","Legs1":2,"Legs2":1,"Max1":null,"Max2":null,"Finishes1":null,"Finishes2":null,"L21_1":null,"L21_2":null,"TwentyOne1":null,"TwentyOne2":null,"Year":2017,"Season":"2017-2018","Rating1":1277.9824011796,"Rating2":1272.6454863661},{"id":1827,"Date":1508457600000,"Player1":"Frank","Player2":"Maik","Legs1":0,"Legs2":2,"Max1":null,"Max2":null,"Finishes1":null,"Finishes2":null,"L21_1":null,"L21_2":null,"TwentyOne1":null,"TwentyOne2":null,"Year":2017,"Season":"2017-2018","Rating1":1266.7762642457,"Rating2":1335.2251565673},{"id":1836,"Date":1508457600000,"Player1":"Frank","Player2":"Bas","Legs1":0,"Legs2":2,"Max1":null,"Max2":null,"Finishes1":null,"Finishes2":null,"L21_1":null,"L21_2":null,"TwentyOne1":null,"TwentyOne2":null,"Year":2017,"Season":"2017-2018","Rating1":1255.71023062,"Rating2":1332.0340914637},{"id":1854,"Date":1509062400000,"Player1":"Frank","Player2":"Elbert","Legs1":2,"Legs2":0,"Max1":null,"Max2":null,"Finishes1":null,"Finishes2":null,"L21_1":null,"L21_2":null,"TwentyOne1":null,"TwentyOne2":null,"Year":2017,"Season":"2017-2018","Rating1":1270.5382941781,"Rating2":1407.7808889208},{"id":1855,"Date":1509062400000,"Player1":"Frank","Player2":"GertJ","Legs1":2,"Legs2":0,"Max1":null,"Max2":null,"Finishes1":null,"Finishes2":null,"L21_1":null,"L21_2":null,"TwentyOne1":null,"TwentyOne2":null,"Year":2017,"Season":"2017-2018","Rating1":1283.1227037636,"Rating2":1291.8214579733},{"id":1858,"Date":1509062400000,"Player1":"Gilbert","Player2":"Frank","Legs1":0,"Legs2":2,"Max1":null,"Max2":null,"Finishes1":null,"Finishes2":null,"L21_1":null,"L21_2":null,"TwentyOne1":null,"TwentyOne2":null,"Year":2017,"Season":"2017-2018","Rating1":996.5767273196,"Rating2":1290.5459764439},{"id":1863,"Date":1509062400000,"Player1":"Jari","Player2":"Frank","Legs1":2,"Legs2":1,"Max1":null,"Max2":null,"Finishes1":null,"Finishes2":null,"L21_1":null,"L21_2":null,"TwentyOne1":null,"TwentyOne2":null,"Year":2017,"Season":"2017-2018","Rating1":1122.0637761753,"Rating2":1283.5788610529},{"id":1884,"Date":1509667200000,"Player1":"Frank","Player2":"Youri","Legs1":0,"Legs2":2,"Max1":null,"Max2":null,"Finishes1":null,"Finishes2":null,"L21_1":null,"L21_2":null,"TwentyOne1":null,"TwentyOne2":null,"Year":2017,"Season":"2017-2018","Rating1":1266.9365339631,"Rating2":1016.6423270897},{"id":1893,"Date":1509667200000,"Player1":"Christa","Player2":"Frank","Legs1":0,"Legs2":2,"Max1":null,"Max2":null,"Finishes1":null,"Finishes2":null,"L21_1":null,"L21_2":null,"TwentyOne1":null,"TwentyOne2":null,"Year":2017,"Season":"2017-2018","Rating1":1003.8519709587,"Rating2":1274.7158031522},{"id":1905,"Date":1509667200000,"Player1":"Menno","Player2":"Frank","Legs1":2,"Legs2":0,"Max1":null,"Max2":null,"Finishes1":null,"Finishes2":null,"L21_1":null,"L21_2":null,"TwentyOne1":null,"TwentyOne2":null,"Year":2017,"Season":"2017-2018","Rating1":1313.1860598043,"Rating2":1263.1807243612},{"id":1909,"Date":1509667200000,"Player1":"Frank","Player2":"John","Legs1":1,"Legs2":2,"Max1":null,"Max2":null,"Finishes1":null,"Finishes2":null,"L21_1":null,"L21_2":null,"TwentyOne1":null,"TwentyOne2":null,"Year":2017,"Season":"2017-2018","Rating1":1255.8086856227,"Rating2":1069.8941361099},{"id":1949,"Date":1510876800000,"Player1":"Frank","Player2":"Bert","Legs1":1,"Legs2":2,"Max1":null,"Max2":null,"Finishes1":null,"Finishes2":null,"L21_1":null,"L21_2":null,"TwentyOne1":null,"TwentyOne2":null,"Year":2017,"Season":"2017-2018","Rating1":1256.0636787006,"Rating2":1513.1256754578},{"id":1955,"Date":1510876800000,"Player1":"Frank","Player2":"GertJ","Legs1":2,"Legs2":0,"Max1":null,"Max2":null,"Finishes1":null,"Finishes2":null,"L21_1":null,"L21_2":null,"TwentyOne1":null,"TwentyOne2":null,"Year":2017,"Season":"2017-2018","Rating1":1269.2337149123,"Rating2":1310.8616141594},{"id":1962,"Date":1510876800000,"Player1":"Maik","Player2":"Frank","Legs1":2,"Legs2":0,"Max1":null,"Max2":null,"Finishes1":null,"Finishes2":null,"L21_1":null,"L21_2":null,"TwentyOne1":null,"TwentyOne2":null,"Year":2017,"Season":"2017-2018","Rating1":1295.6123203778,"Rating2":1257.4863501531},{"id":1969,"Date":1510876800000,"Player1":"Ernie","Player2":"Frank","Legs1":0,"Legs2":2,"Max1":null,"Max2":null,"Finishes1":null,"Finishes2":null,"L21_1":null,"L21_2":null,"TwentyOne1":null,"TwentyOne2":null,"Year":2017,"Season":"2017-2018","Rating1":992.2537001271,"Rating2":1265.232650026},{"id":2040,"Date":1512691200000,"Player1":"Henri","Player2":"Frank","Legs1":0,"Legs2":2,"Max1":null,"Max2":null,"Finishes1":null,"Finishes2":null,"L21_1":null,"L21_2":null,"TwentyOne1":null,"TwentyOne2":null,"Year":2017,"Season":"2017-2018","Rating1":1144.1107013365,"Rating2":1275.3314991307},{"id":2047,"Date":1512691200000,"Player1":"Otto","Player2":"Frank","Legs1":2,"Legs2":1,"Max1":null,"Max2":1.0,"Finishes1":null,"Finishes2":null,"L21_1":null,"L21_2":null,"TwentyOne1":null,"TwentyOne2":null,"Year":2017,"Season":"2017-2018","Rating1":1052.6209996772,"Rating2":1267.4899485558},{"id":2053,"Date":1512691200000,"Player1":"Bas","Player2":"Frank","Legs1":2,"Legs2":1,"Max1":null,"Max2":null,"Finishes1":null,"Finishes2":null,"L21_1":null,"L21_2":null,"TwentyOne1":null,"TwentyOne2":null,"Year":2017,"Season":"2017-2018","Rating1":1355.8396091269,"Rating2":1264.9645908213},{"id":2060,"Date":1512691200000,"Player1":"Frank","Player2":"Elbert","Legs1":1,"Legs2":2,"Max1":null,"Max2":null,"Finishes1":null,"Finishes2":null,"L21_1":null,"L21_2":null,"TwentyOne1":null,"TwentyOne2":null,"Year":2017,"Season":"2017-2018","Rating1":1264.4891223686,"Rating2":1475.7238932931},{"id":2067,"Date":1513296000000,"Player1":"Frank","Player2":"Maik","Legs1":2,"Legs2":0,"Max1":null,"Max2":null,"Finishes1":null,"Finishes2":null,"L21_1":null,"L21_2":null,"TwentyOne1":null,"TwentyOne2":null,"Year":2017,"Season":"2017-2018","Rating1":1276.6172188223,"Rating2":1259.7788520714},{"id":2075,"Date":1513296000000,"Player1":"Andor","Player2":"Frank","Legs1":1,"Legs2":2,"Max1":null,"Max2":null,"Finishes1":null,"Finishes2":null,"L21_1":null,"L21_2":null,"TwentyOne1":null,"TwentyOne2":null,"Year":2017,"Season":"2017-2018","Rating1":1459.0531184009,"Rating2":1283.8130965067},{"id":2080,"Date":1513296000000,"Player1":"Frank","Player2":"Christa","Legs1":2,"Legs2":1,"Max1":null,"Max2":null,"Finishes1":null,"Finishes2":null,"L21_1":null,"L21_2":null,"TwentyOne1":null,"TwentyOne2":null,"Year":2017,"Season":"2017-2018","Rating1":1283.1687283336,"Rating2":1000.7396002466},{"id":2085,"Date":1513296000000,"Player1":"Johan","Player2":"Frank","Legs1":1,"Legs2":2,"Max1":null,"Max2":null,"Finishes1":null,"Finishes2":null,"L21_1":null,"L21_2":null,"TwentyOne1":null,"TwentyOne2":null,"Year":2017,"Season":"2017-2018","Rating1":1323.5841991162,"Rating2":1287.9481172074},{"id":2100,"Date":1513900800000,"Player1":"GertJ","Player2":"Frank","Legs1":1,"Legs2":2,"Max1":null,"Max2":null,"Finishes1":null,"Finishes2":null,"L21_1":null,"L21_2":null,"TwentyOne1":null,"TwentyOne2":null,"Year":2017,"Season":"2017-2018","Rating1":1342.5809079312,"Rating2":1292.9758944764},{"id":2107,"Date":1513900800000,"Player1":"Christa","Player2":"Frank","Legs1":0,"Legs2":2,"Max1":null,"Max2":null,"Finishes1":null,"Finishes2":null,"L21_1":null,"L21_2":null,"TwentyOne1":null,"TwentyOne2":null,"Year":2017,"Season":"2017-2018","Rating1":1001.400387773,"Rating2":1300.3240478257},{"id":2124,"Date":1513900800000,"Player1":"Frank","Player2":"Andor","Legs1":1,"Legs2":2,"Max1":null,"Max2":null,"Finishes1":null,"Finishes2":null,"L21_1":null,"L21_2":null,"TwentyOne1":null,"TwentyOne2":null,"Year":2017,"Season":"2017-2018","Rating1":1298.9541801343,"Rating2":1456.5057517649},{"id":2131,"Date":1513900800000,"Player1":"Frank","Player2":"Henri","Legs1":2,"Legs2":1,"Max1":null,"Max2":null,"Finishes1":null,"Finishes2":null,"L21_1":null,"L21_2":null,"TwentyOne1":null,"TwentyOne2":null,"Year":2017,"Season":"2017-2018","Rating1":1300.5210854822,"Rating2":1154.5168887634},{"id":2202,"Date":1516320000000,"Player1":"Frank","Player2":"Christa","Legs1":2,"Legs2":0,"Max1":null,"Max2":null,"Finishes1":null,"Finishes2":null,"L21_1":null,"L21_2":null,"TwentyOne1":null,"TwentyOne2":null,"Year":2018,"Season":"2017-2018","Rating1":1307.9149341919,"Rating2":1012.0084925367},{"id":2208,"Date":1516320000000,"Player1":"Maik","Player2":"Frank","Legs1":0,"Legs2":2,"Max1":null,"Max2":null,"Finishes1":null,"Finishes2":null,"L21_1":null,"L21_2":null,"TwentyOne1":null,"TwentyOne2":null,"Year":2018,"Season":"2017-2018","Rating1":1304.1770841534,"Rating2":1320.0601165939},{"id":2214,"Date":1516320000000,"Player1":"Frank","Player2":"Bert","Legs1":0,"Legs2":2,"Max1":null,"Max2":null,"Finishes1":null,"Finishes2":null,"L21_1":null,"L21_2":null,"TwentyOne1":null,"TwentyOne2":null,"Year":2018,"Season":"2017-2018","Rating1":1310.9172309479,"Rating2":1497.8839448028},{"id":2225,"Date":1516320000000,"Player1":"Frank","Player2":"Henri","Legs1":2,"Legs2":1,"Max1":null,"Max2":null,"Finishes1":null,"Finishes2":null,"L21_1":null,"L21_2":null,"TwentyOne1":null,"TwentyOne2":null,"Year":2018,"Season":"2017-2018","Rating1":1312.0706642412,"Rating2":1141.7301872322},{"id":2235,"Date":1516924800000,"Player1":"Jari","Player2":"Frank","Legs1":1,"Legs2":2,"Max1":null,"Max2":null,"Finishes1":null,"Finishes2":null,"L21_1":null,"L21_2":null,"TwentyOne1":null,"TwentyOne2":null,"Year":2018,"Season":"2017-2018","Rating1":1142.1924325143,"Rating2":1313.212648972},{"id":2240,"Date":1516924800000,"Player1":"Frank","Player2":"Maik","Legs1":2,"Legs2":0,"Max1":null,"Max2":null,"Finishes1":null,"Finishes2":null,"L21_1":null,"L21_2":null,"TwentyOne1":null,"TwentyOne2":null,"Year":2018,"Season":"2017-2018","Rating1":1325.1393548999,"Rating2":1297.0417287944},{"id":2245,"Date":1516924800000,"Player1":"Bas","Player2":"Frank","Legs1":2,"Legs2":0,"Max1":null,"Max2":null,"Finishes1":null,"Finishes2":null,"L21_1":null,"L21_2":null,"TwentyOne1":null,"TwentyOne2":null,"Year":2018,"Season":"2017-2018","Rating1":1397.8263660371,"Rating2":1314.2029517768},{"id":2251,"Date":1516924800000,"Player1":"Christa","Player2":"Frank","Legs1":0,"Legs2":2,"Max1":null,"Max2":null,"Finishes1":null,"Finishes2":null,"L21_1":null,"L21_2":null,"TwentyOne1":null,"TwentyOne2":null,"Year":2018,"Season":"2017-2018","Rating1":993.0842166413,"Rating2":1321.1187351355},{"id":2260,"Date":1517529600000,"Player1":"Frank","Player2":"Bas","Legs1":2,"Legs2":0,"Max1":null,"Max2":null,"Finishes1":null,"Finishes2":null,"L21_1":null,"L21_2":null,"TwentyOne1":null,"TwentyOne2":null,"Year":2018,"Season":"2017-2018","Rating1":1334.6089818781,"Rating2":1394.3703869351},{"id":2266,"Date":1517529600000,"Player1":"Frank","Player2":"Maik","Legs1":0,"Legs2":2,"Max1":null,"Max2":null,"Finishes1":null,"Finishes2":null,"L21_1":null,"L21_2":null,"TwentyOne1":null,"TwentyOne2":null,"Year":2018,"Season":"2017-2018","Rating1":1322.1753076085,"Rating2":1321.919402501},{"id":2274,"Date":1517529600000,"Player1":"Harry","Player2":"Frank","Legs1":0,"Legs2":2,"Max1":null,"Max2":null,"Finishes1":null,"Finishes2":null,"L21_1":null,"L21_2":null,"TwentyOne1":null,"TwentyOne2":null,"Year":2018,"Season":"2017-2018","Rating1":1121.0327996731,"Rating2":1330.9353430911},{"id":2278,"Date":1517529600000,"Player1":"Marianne","Player2":"Frank","Legs1":1,"Legs2":2,"Max1":null,"Max2":null,"Finishes1":null,"Finishes2":null,"L21_1":null,"L21_2":null,"TwentyOne1":null,"TwentyOne2":null,"Year":2018,"Season":"2017-2018","Rating1":1002.8045223062,"Rating2":1329.6374044882},{"id":2295,"Date":1518134400000,"Player1":"Bas","Player2":"Frank","Legs1":0,"Legs2":2,"Max1":null,"Max2":null,"Finishes1":null,"Finishes2":null,"L21_1":null,"L21_2":null,"TwentyOne1":null,"TwentyOne2":null,"Year":2018,"Season":"2017-2018","Rating1":1396.1768129498,"Rating2":1343.0114080015},{"id":2303,"Date":1518134400000,"Player1":"Youri","Player2":"Frank","Legs1":0,"Legs2":2,"Max1":null,"Max2":null,"Finishes1":null,"Finishes2":null,"L21_1":null,"L21_2":null,"TwentyOne1":null,"TwentyOne2":null,"Year":2018,"Season":"2017-2018","Rating1":1013.4685821467,"Rating2":1349.8067542121},{"id":2309,"Date":1518134400000,"Player1":"Frank","Player2":"Maik","Legs1":2,"Legs2":1,"Max1":null,"Max2":null,"Finishes1":null,"Finishes2":null,"L21_1":null,"L21_2":null,"TwentyOne1":null,"TwentyOne2":null,"Year":2018,"Season":"2017-2018","Rating1":1353.1316323712,"Rating2":1307.3469924893},{"id":2319,"Date":1518134400000,"Player1":"Frank","Player2":"Otto","Legs1":2,"Legs2":0,"Max1":null,"Max2":null,"Finishes1":null,"Finishes2":null,"L21_1":null,"L21_2":null,"TwentyOne1":null,"TwentyOne2":null,"Year":2018,"Season":"2017-2018","Rating1":1359.5101829023,"Rating2":993.6973790611},{"id":2329,"Date":1518739200000,"Player1":"Elbert","Player2":"Frank","Legs1":2,"Legs2":1,"Max1":null,"Max2":null,"Finishes1":null,"Finishes2":null,"L21_1":null,"L21_2":null,"TwentyOne1":null,"TwentyOne2":null,"Year":2018,"Season":"2017-2018","Rating1":1536.3792336766,"Rating2":1358.4836729906},{"id":2333,"Date":1518739200000,"Player1":"Frank","Player2":"Marianne","Legs1":2,"Legs2":0,"Max1":null,"Max2":null,"Finishes1":null,"Finishes2":null,"L21_1":null,"L21_2":null,"TwentyOne1":null,"TwentyOne2":null,"Year":2018,"Season":"2017-2018","Rating1":1364.7893247145,"Rating2":993.6943482761},{"id":2338,"Date":1518739200000,"Player1":"Bas","Player2":"Frank","Legs1":2,"Legs2":1,"Max1":null,"Max2":null,"Finishes1":null,"Finishes2":null,"L21_1":null,"L21_2":null,"TwentyOne1":null,"TwentyOne2":null,"Year":2018,"Season":"2017-2018","Rating1":1394.414260293,"Rating2":1361.2394131868},{"id":2344,"Date":1518739200000,"Player1":"Ernie","Player2":"Frank","Legs1":0,"Legs2":2,"Max1":null,"Max2":null,"Finishes1":null,"Finishes2":null,"L21_1":null,"L21_2":null,"TwentyOne1":null,"TwentyOne2":null,"Year":2018,"Season":"2017-2018","Rating1":1002.3878276415,"Rating2":1367.6259283963},{"id":2368,"Date":1519344000000,"Player1":"Frank","Player2":"Bert","Legs1":1,"Legs2":2,"Max1":null,"Max2":null,"Finishes1":null,"Finishes2":null,"L21_1":null,"L21_2":null,"TwentyOne1":null,"TwentyOne2":null,"Year":2018,"Season":"2017-2018","Rating1":1365.7834236257,"Rating2":1495.773065162},{"id":2380,"Date":1519344000000,"Player1":"Otto","Player2":"Frank","Legs1":2,"Legs2":1,"Max1":null,"Max2":null,"Finishes1":null,"Finishes2":null,"L21_1":null,"L21_2":null,"TwentyOne1":null,"TwentyOne2":null,"Year":2018,"Season":"2017-2018","Rating1":1044.4028019302,"Rating2":1356.4678780968},{"id":2385,"Date":1519344000000,"Player1":"Frank","Player2":"Christa","Legs1":2,"Legs2":1,"Max1":null,"Max2":null,"Finishes1":null,"Finishes2":null,"L21_1":null,"L21_2":null,"TwentyOne1":null,"TwentyOne2":null,"Year":2018,"Season":"2017-2018","Rating1":1354.9658181982,"Rating2":1013.7191682629},{"id":2387,"Date":1519344000000,"Player1":"JR","Player2":"Frank","Legs1":1,"Legs2":2,"Max1":null,"Max2":null,"Finishes1":null,"Finishes2":null,"L21_1":null,"L21_2":null,"TwentyOne1":null,"TwentyOne2":null,"Year":2018,"Season":"2017-2018","Rating1":1077.5661341852,"Rating2":1354.4062716265},{"id":2388,"Date":1519948800000,"Player1":"Frank","Player2":"JR","Legs1":2,"Legs2":1,"Max1":null,"Max2":null,"Finishes1":null,"Finishes2":null,"L21_1":null,"L21_2":null,"TwentyOne1":null,"TwentyOne2":null,"Year":2018,"Season":"2017-2018","Rating1":1353.8632710921,"Rating2":1078.1091347196},{"id":2406,"Date":1519948800000,"Player1":"Frank","Player2":"Otto","Legs1":1,"Legs2":2,"Max1":null,"Max2":null,"Finishes1":null,"Finishes2":null,"L21_1":null,"L21_2":null,"TwentyOne1":null,"TwentyOne2":null,"Year":2018,"Season":"2017-2018","Rating1":1344.813649209,"Rating2":1051.1478369572},{"id":2410,"Date":1519948800000,"Player1":"Youri","Player2":"Frank","Legs1":0,"Legs2":2,"Max1":null,"Max2":null,"Finishes1":null,"Finishes2":null,"L21_1":null,"L21_2":null,"TwentyOne1":null,"TwentyOne2":null,"Year":2018,"Season":"2017-2018","Rating1":995.5003249856,"Rating2":1351.3314564039},{"id":2421,"Date":1519948800000,"Player1":"Christa","Player2":"Frank","Legs1":1,"Legs2":2,"Max1":null,"Max2":null,"Finishes1":null,"Finishes2":null,"L21_1":null,"L21_2":null,"TwentyOne1":null,"TwentyOne2":null,"Year":2018,"Season":"2017-2018","Rating1":1021.4377658121,"Rating2":1350.0086912144},{"id":2424,"Date":1521158400000,"Player1":"Frank","Player2":"Bas","Legs1":2,"Legs2":0,"Max1":null,"Max2":null,"Finishes1":null,"Finishes2":null,"L21_1":null,"L21_2":null,"TwentyOne1":null,"TwentyOne2":null,"Year":2018,"Season":"2017-2018","Rating1":1363.3932277631,"Rating2":1417.1556575129},{"id":2430,"Date":1521158400000,"Player1":"Johan","Player2":"Frank","Legs1":2,"Legs2":1,"Max1":null,"Max2":null,"Finishes1":null,"Finishes2":null,"L21_1":null,"L21_2":null,"TwentyOne1":null,"TwentyOne2":null,"Year":2018,"Season":"2017-2018","Rating1":1443.8338171173,"Rating2":1360.7308280287},{"id":2441,"Date":1521158400000,"Player1":"Paplip","Player2":"Frank","Legs1":2,"Legs2":1,"Max1":null,"Max2":null,"Finishes1":null,"Finishes2":null,"L21_1":null,"L21_2":null,"TwentyOne1":null,"TwentyOne2":null,"Year":2018,"Season":"2017-2018","Rating1":1394.2640950618,"Rating2":1357.2494830113},{"id":2448,"Date":1521158400000,"Player1":"Frank","Player2":"Andor","Legs1":0,"Legs2":2,"Max1":null,"Max2":null,"Finishes1":null,"Finishes2":null,"L21_1":null,"L21_2":null,"TwentyOne1":null,"TwentyOne2":null,"Year":2018,"Season":"2017-2018","Rating1":1347.9370007922,"Rating2":1524.8683243074},{"id":2450,"Date":1520553600000,"Player1":"Henri","Player2":"Frank","Legs1":2,"Legs2":1,"Max1":null,"Max2":null,"Finishes1":null,"Finishes2":null,"L21_1":null,"L21_2":null,"TwentyOne1":null,"TwentyOne2":null,"Year":2018,"Season":"2017-2018","Rating1":1149.4480632436,"Rating2":1340.4810612648},{"id":2469,"Date":1520553600000,"Player1":"Frank","Player2":"Menno","Legs1":1,"Legs2":2,"Max1":null,"Max2":null,"Finishes1":null,"Finishes2":null,"L21_1":null,"L21_2":null,"TwentyOne1":null,"TwentyOne2":null,"Year":2018,"Season":"2017-2018","Rating1":1335.1523911042,"Rating2":1268.5551097602},{"id":2478,"Date":1520553600000,"Player1":"Paplip","Player2":"Frank","Legs1":2,"Legs2":1,"Max1":null,"Max2":null,"Finishes1":null,"Finishes2":null,"L21_1":null,"L21_2":null,"TwentyOne1":null,"TwentyOne2":null,"Year":2018,"Season":"2017-2018","Rating1":1386.1390909906,"Rating2":1331.9767584836},{"id":2484,"Date":1520553600000,"Player1":"Frank","Player2":"Gilbert","Legs1":2,"Legs2":0,"Max1":null,"Max2":null,"Finishes1":null,"Finishes2":null,"L21_1":null,"L21_2":null,"TwentyOne1":null,"TwentyOne2":null,"Year":2018,"Season":"2017-2018","Rating1":1338.6434517565,"Rating2":993.3333067271},{"id":2523,"Date":1522368000000,"Player1":"Frank","Player2":"Andor","Legs1":0,"Legs2":2,"Max1":null,"Max2":null,"Finishes1":null,"Finishes2":null,"L21_1":null,"L21_2":null,"TwentyOne1":null,"TwentyOne2":null,"Year":2018,"Season":"2017-2018","Rating1":1330.3061385137,"Rating2":1566.0528799284},{"id":2530,"Date":1522368000000,"Player1":"Frank","Player2":"Elbert","Legs1":0,"Legs2":2,"Max1":null,"Max2":null,"Finishes1":null,"Finishes2":null,"L21_1":null,"L21_2":null,"TwentyOne1":null,"TwentyOne2":null,"Year":2018,"Season":"2017-2018","Rating1":1322.3529271602,"Rating2":1582.1358368417},{"id":2533,"Date":1522368000000,"Player1":"John","Player2":"Frank","Legs1":0,"Legs2":2,"Max1":null,"Max2":null,"Finishes1":null,"Finishes2":null,"L21_1":null,"L21_2":null,"TwentyOne1":null,"TwentyOne2":null,"Year":2018,"Season":"2017-2018","Rating1":1078.8694929514,"Rating2":1330.4364047583},{"id":2542,"Date":1522368000000,"Player1":"Henri","Player2":"Frank","Legs1":0,"Legs2":2,"Max1":null,"Max2":null,"Finishes1":null,"Finishes2":104.0,"L21_1":null,"L21_2":null,"TwentyOne1":null,"TwentyOne2":null,"Year":2018,"Season":"2017-2018","Rating1":1176.0545277463,"Rating2":1339.9705859509},{"id":2564,"Date":1523577600000,"Player1":"Elbert","Player2":"Frank","Legs1":2,"Legs2":0,"Max1":null,"Max2":null,"Finishes1":null,"Finishes2":null,"L21_1":null,"L21_2":null,"TwentyOne1":null,"TwentyOne2":null,"Year":2018,"Season":"2017-2018","Rating1":1593.8418927021,"Rating2":1332.0490754653},{"id":2579,"Date":1523577600000,"Player1":"Frank","Player2":"GertJ","Legs1":1,"Legs2":2,"Max1":null,"Max2":null,"Finishes1":null,"Finishes2":null,"L21_1":null,"L21_2":null,"TwentyOne1":null,"TwentyOne2":null,"Year":2018,"Season":"2017-2018","Rating1":1327.5923198421,"Rating2":1310.0441874677},{"id":2591,"Date":1523577600000,"Player1":"Frank","Player2":"Otto","Legs1":0,"Legs2":2,"Max1":null,"Max2":null,"Finishes1":null,"Finishes2":null,"L21_1":null,"L21_2":null,"TwentyOne1":null,"TwentyOne2":null,"Year":2018,"Season":"2017-2018","Rating1":1310.3599520497,"Rating2":1020.0981223075},{"id":2595,"Date":1523577600000,"Player1":"Gilbert","Player2":"Frank","Legs1":0,"Legs2":2,"Max1":null,"Max2":null,"Finishes1":null,"Finishes2":null,"L21_1":null,"L21_2":null,"TwentyOne1":null,"TwentyOne2":null,"Year":2018,"Season":"2017-2018","Rating1":993.0296363741,"Rating2":1317.3303156756},{"id":2620,"Date":1535673600000,"Player1":"Bert","Player2":"Frank","Legs1":2,"Legs2":0,"Max1":null,"Max2":null,"Finishes1":116.0,"Finishes2":null,"L21_1":null,"L21_2":null,"TwentyOne1":null,"TwentyOne2":null,"Year":2018,"Season":"2018-2019","Rating1":1526.7169819261,"Rating2":1308.7039718902},{"id":2639,"Date":1535673600000,"Player1":"Gilbert","Player2":"Frank","Legs1":0,"Legs2":2,"Max1":null,"Max2":null,"Finishes1":null,"Finishes2":null,"L21_1":null,"L21_2":null,"TwentyOne1":null,"TwentyOne2":null,"Year":2018,"Season":"2018-2019","Rating1":993.0060390046,"Rating2":1315.6979328857},{"id":2640,"Date":1535673600000,"Player1":"Frank","Player2":"Henri","Legs1":2,"Legs2":0,"Max1":null,"Max2":null,"Finishes1":null,"Finishes2":null,"L21_1":null,"L21_2":null,"TwentyOne1":null,"TwentyOne2":null,"Year":2018,"Season":"2018-2019","Rating1":1325.4633011637,"Rating2":1175.0064772174},{"id":2650,"Date":1535673600000,"Player1":"Frank","Player2":"Johan","Legs1":0,"Legs2":2,"Max1":null,"Max2":null,"Finishes1":null,"Finishes2":null,"L21_1":null,"L21_2":null,"TwentyOne1":null,"TwentyOne2":null,"Year":2018,"Season":"2018-2019","Rating1":1315.6222477556,"Rating2":1461.6958384309},{"id":2691,"Date":1536883200000,"Player1":"Frank","Player2":"Elbert","Legs1":2,"Legs2":0,"Max1":null,"Max2":null,"Finishes1":null,"Finishes2":null,"L21_1":null,"L21_2":null,"TwentyOne1":null,"TwentyOne2":null,"Year":2018,"Season":"2018-2019","Rating1":1331.9582279707,"Rating2":1562.2371327757},{"id":2699,"Date":1536883200000,"Player1":"Johan","Player2":"Frank","Legs1":2,"Legs2":1,"Max1":null,"Max2":null,"Finishes1":null,"Finishes2":null,"L21_1":null,"L21_2":null,"TwentyOne1":null,"TwentyOne2":null,"Year":2018,"Season":"2018-2019","Rating1":1453.7147602719,"Rating2":1330.0069309836},{"id":2708,"Date":1536883200000,"Player1":"Frank","Player2":"Andor","Legs1":1,"Legs2":2,"Max1":null,"Max2":null,"Finishes1":null,"Finishes2":null,"L21_1":null,"L21_2":null,"TwentyOne1":null,"TwentyOne2":null,"Year":2018,"Season":"2018-2019","Rating1":1330.4616613917,"Rating2":1600.4450082347},{"id":2721,"Date":1536883200000,"Player1":"Maik","Player2":"Frank","Legs1":0,"Legs2":2,"Max1":null,"Max2":null,"Finishes1":null,"Finishes2":null,"L21_1":null,"L21_2":null,"TwentyOne1":null,"TwentyOne2":null,"Year":2018,"Season":"2018-2019","Rating1":1289.9610647113,"Rating2":1341.9611200775},{"id":2762,"Date":1538092800000,"Player1":"Otto","Player2":"Frank","Legs1":0,"Legs2":2,"Max1":null,"Max2":null,"Finishes1":null,"Finishes2":null,"L21_1":null,"L21_2":null,"TwentyOne1":null,"TwentyOne2":null,"Year":2018,"Season":"2018-2019","Rating1":1013.0802016223,"Rating2":1348.7658827104},{"id":2771,"Date":1538092800000,"Player1":"Bas","Player2":"Frank","Legs1":2,"Legs2":1,"Max1":null,"Max2":null,"Finishes1":null,"Finishes2":null,"L21_1":null,"L21_2":null,"TwentyOne1":null,"TwentyOne2":null,"Year":2018,"Season":"2018-2019","Rating1":1453.3640799955,"Rating2":1346.5207845815},{"id":2779,"Date":1538092800000,"Player1":"Frank","Player2":"GertJ","Legs1":2,"Legs2":1,"Max1":null,"Max2":null,"Finishes1":null,"Finishes2":null,"L21_1":null,"L21_2":null,"TwentyOne1":null,"TwentyOne2":null,"Year":2018,"Season":"2018-2019","Rating1":1350.4915523562,"Rating2":1340.8572942398},{"id":2787,"Date":1538092800000,"Player1":"Frank","Player2":"Andor","Legs1":0,"Legs2":2,"Max1":null,"Max2":null,"Finishes1":null,"Finishes2":null,"L21_1":null,"L21_2":null,"TwentyOne1":null,"TwentyOne2":null,"Year":2018,"Season":"2018-2019","Rating1":1343.0435394248,"Rating2":1635.387338376},{"id":2831,"Date":1539302400000,"Player1":"John","Player2":"Frank","Legs1":1,"Legs2":2,"Max1":null,"Max2":null,"Finishes1":null,"Finishes2":null,"L21_1":null,"L21_2":null,"TwentyOne1":null,"TwentyOne2":null,"Year":2018,"Season":"2018-2019","Rating1":1029.2483518111,"Rating2":1341.9496042333},{"id":2841,"Date":1539302400000,"Player1":"Frank","Player2":"Otto","Legs1":2,"Legs2":1,"Max1":null,"Max2":null,"Finishes1":null,"Finishes2":null,"L21_1":null,"L21_2":null,"TwentyOne1":null,"TwentyOne2":null,"Year":2018,"Season":"2018-2019","Rating1":1340.8847896553,"Rating2":1030.1796214801},{"id":2851,"Date":1539302400000,"Player1":"Frank","Player2":"Erik","Legs1":2,"Legs2":1,"Max1":null,"Max2":null,"Finishes1":null,"Finishes2":null,"L21_1":null,"L21_2":null,"TwentyOne1":null,"TwentyOne2":null,"Year":2018,"Season":"2018-2019","Rating1":1343.3028994851,"Rating2":1246.3296536772},{"id":2865,"Date":1539302400000,"Player1":"Christa","Player2":"Frank","Legs1":1,"Legs2":2,"Max1":null,"Max2":null,"Finishes1":null,"Finishes2":null,"L21_1":null,"L21_2":null,"TwentyOne1":null,"TwentyOne2":null,"Year":2018,"Season":"2018-2019","Rating1":1006.0097246436,"Rating2":1341.8765544892},{"id":2869,"Date":1539907200000,"Player1":"Frank","Player2":"Christa","Legs1":2,"Legs2":0,"Max1":null,"Max2":null,"Finishes1":null,"Finishes2":null,"L21_1":null,"L21_2":null,"TwentyOne1":null,"TwentyOne2":null,"Year":2018,"Season":"2018-2019","Rating1":1348.4894727928,"Rating2":999.39680634},{"id":2877,"Date":1539907200000,"Player1":"Bert","Player2":"Frank","Legs1":2,"Legs2":1,"Max1":null,"Max2":null,"Finishes1":null,"Finishes2":null,"L21_1":null,"L21_2":null,"TwentyOne1":null,"TwentyOne2":null,"Year":2018,"Season":"2018-2019","Rating1":1517.1140535046,"Rating2":1347.3267189644},{"id":2885,"Date":1539907200000,"Player1":"Frank","Player2":"Jari","Legs1":2,"Legs2":0,"Max1":null,"Max2":null,"Finishes1":null,"Finishes2":null,"L21_1":null,"L21_2":null,"TwentyOne1":null,"TwentyOne2":null,"Year":2018,"Season":"2018-2019","Rating1":1357.3665378834,"Rating2":1222.7547625728},{"id":2893,"Date":1539907200000,"Player1":"Otto","Player2":"Frank","Legs1":0,"Legs2":2,"Max1":null,"Max2":null,"Finishes1":null,"Finishes2":null,"L21_1":null,"L21_2":null,"TwentyOne1":null,"TwentyOne2":null,"Year":2018,"Season":"2018-2019","Rating1":1010.910650036,"Rating2":1363.9240094845},{"id":3135,"Date":1544745600000,"Player1":"Andor","Player2":"Frank","Legs1":1,"Legs2":2,"Max1":null,"Max2":null,"Finishes1":null,"Finishes2":null,"L21_1":null,"L21_2":null,"TwentyOne1":null,"TwentyOne2":null,"Year":2018,"Season":"2018-2019","Rating1":1589.439023053,"Rating2":1371.8096541601},{"id":3145,"Date":1544745600000,"Player1":"Frank","Player2":"Reyn","Legs1":0,"Legs2":2,"Max1":null,"Max2":null,"Finishes1":null,"Finishes2":null,"L21_1":null,"L21_2":null,"TwentyOne1":null,"TwentyOne2":null,"Year":2018,"Season":"2018-2019","Rating1":1356.3477740949,"Rating2":1180.9514948866},{"id":3152,"Date":1544745600000,"Player1":"Bas","Player2":"Frank","Legs1":2,"Legs2":1,"Max1":null,"Max2":null,"Finishes1":null,"Finishes2":null,"L21_1":null,"L21_2":null,"TwentyOne1":null,"TwentyOne2":null,"Year":2018,"Season":"2018-2019","Rating1":1475.4245436804,"Rating2":1354.3507510817},{"id":3163,"Date":1544745600000,"Player1":"Frank","Player2":"Otto","Legs1":2,"Legs2":0,"Max1":null,"Max2":null,"Finishes1":null,"Finishes2":null,"L21_1":null,"L21_2":null,"TwentyOne1":null,"TwentyOne2":null,"Year":2018,"Season":"2018-2019","Rating1":1360.8478529685,"Rating2":1003.541419328},{"id":3171,"Date":1545350400000,"Player1":"Pietra","Player2":"Frank","Legs1":0,"Legs2":2,"Max1":null,"Max2":null,"Finishes1":null,"Finishes2":null,"L21_1":null,"L21_2":null,"TwentyOne1":null,"TwentyOne2":null,"Year":2018,"Season":"2018-2019","Rating1":1104.2842896045,"Rating2":1368.7276594885},{"id":3182,"Date":1545350400000,"Player1":"Frank","Player2":"Frans","Legs1":2,"Legs2":0,"Max1":null,"Max2":null,"Finishes1":null,"Finishes2":null,"L21_1":null,"L21_2":null,"TwentyOne1":null,"TwentyOne2":null,"Year":2018,"Season":"2018-2019","Rating1":1379.3854243082,"Rating2":1280.0199275003},{"id":3190,"Date":1545350400000,"Player1":"Otto","Player2":"Frank","Legs1":2,"Legs2":0,"Max1":null,"Max2":null,"Finishes1":null,"Finishes2":null,"L21_1":null,"L21_2":null,"TwentyOne1":null,"TwentyOne2":null,"Year":2018,"Season":"2018-2019","Rating1":1028.1101439997,"Rating2":1361.5499131543},{"id":3202,"Date":1545350400000,"Player1":"Frank","Player2":"Menno","Legs1":2,"Legs2":1,"Max1":null,"Max2":null,"Finishes1":null,"Finishes2":null,"L21_1":null,"L21_2":null,"TwentyOne1":null,"TwentyOne2":null,"Year":2018,"Season":"2018-2019","Rating1":1364.9214091651,"Rating2":1321.7509752058},{"id":3213,"Date":1546560000000,"Player1":"Johan","Player2":"Frank","Legs1":0,"Legs2":2,"Max1":null,"Max2":null,"Finishes1":null,"Finishes2":null,"L21_1":null,"L21_2":null,"TwentyOne1":null,"TwentyOne2":null,"Year":2019,"Season":"2018-2019","Rating1":1407.6215187582,"Rating2":1377.8805601057},{"id":3224,"Date":1546560000000,"Player1":"Frank","Player2":"Bert","Legs1":0,"Legs2":2,"Max1":null,"Max2":null,"Finishes1":null,"Finishes2":null,"L21_1":null,"L21_2":null,"TwentyOne1":null,"TwentyOne2":null,"Year":2019,"Season":"2018-2019","Rating1":1368.945069165,"Rating2":1568.2853023028},{"id":3232,"Date":1546560000000,"Player1":"Henri","Player2":"Frank","Legs1":0,"Legs2":2,"Max1":null,"Max2":null,"Finishes1":null,"Finishes2":null,"L21_1":null,"L21_2":null,"TwentyOne1":null,"TwentyOne2":null,"Year":2019,"Season":"2018-2019","Rating1":1105.6423055107,"Rating2":1376.7209859786},{"id":3235,"Date":1546560000000,"Player1":"Frank","Player2":"Menno","Legs1":0,"Legs2":2,"Max1":null,"Max2":null,"Finishes1":null,"Finishes2":null,"L21_1":null,"L21_2":null,"TwentyOne1":null,"TwentyOne2":null,"Year":2019,"Season":"2018-2019","Rating1":1363.2271211102,"Rating2":1303.2601514732},{"id":3246,"Date":1547164800000,"Player1":"John","Player2":"Frank","Legs1":0,"Legs2":2,"Max1":null,"Max2":null,"Finishes1":null,"Finishes2":null,"L21_1":null,"L21_2":null,"TwentyOne1":null,"TwentyOne2":null,"Year":2019,"Season":"2018-2019","Rating1":1034.1569816965,"Rating2":1370.029191033},{"id":3255,"Date":1547164800000,"Player1":"Frank","Player2":"Henri","Legs1":1,"Legs2":2,"Max1":null,"Max2":null,"Finishes1":null,"Finishes2":null,"L21_1":null,"L21_2":null,"TwentyOne1":null,"TwentyOne2":null,"Year":2019,"Season":"2018-2019","Rating1":1361.7284594231,"Rating2":1117.7238123869},{"id":3261,"Date":1547164800000,"Player1":"Christa","Player2":"Frank","Legs1":1,"Legs2":2,"Max1":null,"Max2":null,"Finishes1":null,"Finishes2":null,"L21_1":null,"L21_2":null,"TwentyOne1":null,"TwentyOne2":null,"Year":2019,"Season":"2018-2019","Rating1":1005.6356216509,"Rating2":1360.0435616406},{"id":3271,"Date":1547164800000,"Player1":"Frank","Player2":"Menno","Legs1":0,"Legs2":2,"Max1":null,"Max2":null,"Finishes1":null,"Finishes2":null,"L21_1":null,"L21_2":null,"TwentyOne1":null,"TwentyOne2":null,"Year":2019,"Season":"2018-2019","Rating1":1347.2465583047,"Rating2":1326.6213037707},{"id":3280,"Date":1547769600000,"Player1":"Maik","Player2":"Frank","Legs1":2,"Legs2":1,"Max1":null,"Max2":null,"Finishes1":null,"Finishes2":null,"L21_1":null,"L21_2":null,"TwentyOne1":null,"TwentyOne2":null,"Year":2019,"Season":"2018-2019","Rating1":1283.3616338946,"Rating2":1342.057608345},{"id":3291,"Date":1547769600000,"Player1":"Frank","Player2":"Ernie","Legs1":2,"Legs2":0,"Max1":null,"Max2":null,"Finishes1":null,"Finishes2":null,"L21_1":null,"L21_2":null,"TwentyOne1":null,"TwentyOne2":null,"Year":2019,"Season":"2018-2019","Rating1":1348.5855040045,"Rating2":993.4721043404},{"id":3299,"Date":1547769600000,"Player1":"Johan","Player2":"Frank","Legs1":2,"Legs2":1,"Max1":null,"Max2":null,"Finishes1":null,"Finishes2":null,"L21_1":null,"L21_2":null,"TwentyOne1":null,"TwentyOne2":null,"Year":2019,"Season":"2018-2019","Rating1":1450.5005191976,"Rating2":1346.2942537076},{"id":3301,"Date":1547769600000,"Player1":"Frank","Player2":"Elbert","Legs1":1,"Legs2":2,"Max1":null,"Max2":null,"Finishes1":null,"Finishes2":null,"L21_1":null,"L21_2":null,"TwentyOne1":null,"TwentyOne2":null,"Year":2019,"Season":"2018-2019","Rating1":1346.9619023906,"Rating2":1630.9314631481},{"id":3390,"Date":1549584000000,"Player1":"Bas","Player2":"Frank","Legs1":1,"Legs2":2,"Max1":null,"Max2":null,"Finishes1":null,"Finishes2":null,"L21_1":null,"L21_2":null,"TwentyOne1":null,"TwentyOne2":null,"Year":2019,"Season":"2018-2019","Rating1":1504.4909504579,"Rating2":1353.7477869997},{"id":3401,"Date":1549584000000,"Player1":"Frank","Player2":"Henri","Legs1":2,"Legs2":0,"Max1":null,"Max2":null,"Finishes1":null,"Finishes2":null,"L21_1":null,"L21_2":null,"TwentyOne1":null,"TwentyOne2":null,"Year":2019,"Season":"2018-2019","Rating1":1361.8564402873,"Rating2":1111.8695561564},{"id":3409,"Date":1549584000000,"Player1":"Johan","Player2":"Frank","Legs1":2,"Legs2":1,"Max1":null,"Max2":null,"Finishes1":null,"Finishes2":null,"L21_1":null,"L21_2":null,"TwentyOne1":null,"TwentyOne2":null,"Year":2019,"Season":"2018-2019","Rating1":1464.4759671311,"Rating2":1359.5773131101},{"id":3421,"Date":1549584000000,"Player1":"Frank","Player2":"Christa","Legs1":2,"Legs2":0,"Max1":null,"Max2":null,"Finishes1":null,"Finishes2":null,"L21_1":null,"L21_2":null,"TwentyOne1":null,"TwentyOne2":null,"Year":2019,"Season":"2018-2019","Rating1":1365.9194447307,"Rating2":997.4727619438},{"id":3556,"Date":1552608000000,"Player1":"Frank","Player2":"Gilbert","Legs1":2,"Legs2":0,"Max1":null,"Max2":null,"Finishes1":null,"Finishes2":null,"L21_1":null,"L21_2":null,"TwentyOne1":null,"TwentyOne2":null,"Year":2019,"Season":"2018-2019","Rating1":1372.397892335,"Rating2":1013.759692319},{"id":3565,"Date":1552608000000,"Player1":"Paplip","Player2":"Frank","Legs1":1,"Legs2":2,"Max1":null,"Max2":null,"Finishes1":null,"Finishes2":null,"L21_1":null,"L21_2":null,"TwentyOne1":null,"TwentyOne2":null,"Year":2019,"Season":"2018-2019","Rating1":1457.4992497609,"Rating2":1377.9546799416},{"id":3574,"Date":1552608000000,"Player1":"Frank","Player2":"Otto","Legs1":2,"Legs2":0,"Max1":null,"Max2":null,"Finishes1":null,"Finishes2":null,"L21_1":null,"L21_2":null,"TwentyOne1":null,"TwentyOne2":null,"Year":2019,"Season":"2018-2019","Rating1":1384.0699781751,"Rating2":998.9881330741},{"id":3584,"Date":1552608000000,"Player1":"Andor","Player2":"Frank","Legs1":0,"Legs2":2,"Max1":null,"Max2":null,"Finishes1":null,"Finishes2":null,"L21_1":null,"L21_2":null,"TwentyOne1":null,"TwentyOne2":null,"Year":2019,"Season":"2018-2019","Rating1":1571.8610624847,"Rating2":1399.4824541863},{"id":3629,"Date":1553817600000,"Player1":"Marianne","Player2":"Frank","Legs1":0,"Legs2":2,"Max1":null,"Max2":null,"Finishes1":null,"Finishes2":null,"L21_1":null,"L21_2":null,"TwentyOne1":null,"TwentyOne2":null,"Year":2019,"Season":"2018-2019","Rating1":1013.621042548,"Rating2":1405.5065734632},{"id":3631,"Date":1553817600000,"Player1":"Frank","Player2":"Bert","Legs1":2,"Legs2":1,"Max1":null,"Max2":null,"Finishes1":null,"Finishes2":null,"L21_1":null,"L21_2":null,"TwentyOne1":null,"TwentyOne2":null,"Year":2019,"Season":"2018-2019","Rating1":1411.3808712015,"Rating2":1509.0609612809},{"id":3648,"Date":1553817600000,"Player1":"Gilbert","Player2":"Frank","Legs1":0,"Legs2":2,"Max1":null,"Max2":null,"Finishes1":null,"Finishes2":null,"L21_1":null,"L21_2":null,"TwentyOne1":null,"TwentyOne2":null,"Year":2019,"Season":"2018-2019","Rating1":994.3762024539,"Rating2":1417.0046687477},{"id":3650,"Date":1553817600000,"Player1":"Frank","Player2":"Christa","Legs1":1,"Legs2":2,"Max1":null,"Max2":null,"Finishes1":null,"Finishes2":null,"L21_1":null,"L21_2":null,"TwentyOne1":null,"TwentyOne2":null,"Year":2019,"Season":"2018-2019","Rating1":1406.8322037039,"Rating2":1032.03396993},{"id":3780,"Date":1567123200000,"Player1":"Frank","Player2":"Otto","Legs1":2,"Legs2":0,"Max1":null,"Max2":null,"Finishes1":null,"Finishes2":null,"L21_1":null,"L21_2":null,"TwentyOne1":null,"TwentyOne2":null,"Year":2019,"Season":"2019-2020","Rating1":1413.3968002194,"Rating2":1060.8884357983},{"id":3787,"Date":1567123200000,"Player1":"Pietra","Player2":"Frank","Legs1":2,"Legs2":0,"Max1":null,"Max2":null,"Finishes1":null,"Finishes2":null,"L21_1":null,"L21_2":null,"TwentyOne1":null,"TwentyOne2":null,"Year":2019,"Season":"2019-2020","Rating1":1159.6162705914,"Rating2":1396.9520119395},{"id":3793,"Date":1567123200000,"Player1":"Frank","Player2":"Maik","Legs1":0,"Legs2":2,"Max1":null,"Max2":null,"Finishes1":null,"Finishes2":null,"L21_1":null,"L21_2":null,"TwentyOne1":null,"TwentyOne2":null,"Year":2019,"Season":"2019-2020","Rating1":1383.2387512488,"Rating2":1310.7748740938},{"id":3800,"Date":1567123200000,"Player1":"Paplip","Player2":"Frank","Legs1":2,"Legs2":1,"Max1":null,"Max2":null,"Finishes1":null,"Finishes2":null,"L21_1":null,"L21_2":null,"TwentyOne1":null,"TwentyOne2":null,"Year":2019,"Season":"2019-2020","Rating1":1463.4534016693,"Rating2":1380.5724311614},{"id":3808,"Date":1567728000000,"Player1":"Andor","Player2":"Frank","Legs1":2,"Legs2":0,"Max1":null,"Max2":null,"Finishes1":null,"Finishes2":null,"L21_1":null,"L21_2":null,"TwentyOne1":null,"TwentyOne2":null,"Year":2019,"Season":"2019-2020","Rating1":1583.564843104,"Rating2":1371.8424730336},{"id":3813,"Date":1567728000000,"Player1":"Frank","Player2":"Christa","Legs1":2,"Legs2":0,"Max1":null,"Max2":null,"Finishes1":null,"Finishes2":null,"L21_1":null,"L21_2":null,"TwentyOne1":null,"TwentyOne2":null,"Year":2019,"Season":"2019-2020","Rating1":1378.0351041683,"Rating2":998.670207569},{"id":3817,"Date":1567728000000,"Player1":"Jari","Player2":"Frank","Legs1":2,"Legs2":0,"Max1":null,"Max2":null,"Finishes1":null,"Finishes2":null,"L21_1":null,"L21_2":null,"TwentyOne1":null,"TwentyOne2":null,"Year":2019,"Season":"2019-2020","Rating1":1211.6653478467,"Rating2":1362.9711691653},{"id":3827,"Date":1567728000000,"Player1":"Frank","Player2":"Otto","Legs1":1,"Legs2":2,"Max1":null,"Max2":null,"Finishes1":null,"Finishes2":null,"L21_1":null,"L21_2":null,"TwentyOne1":null,"TwentyOne2":null,"Year":2019,"Season":"2019-2020","Rating1":1354.3550857943,"Rating2":1089.793750035},{"id":3947,"Date":1571356800000,"Player1":"Frank","Player2":"Johan","Legs1":2,"Legs2":1,"Max1":null,"Max2":null,"Finishes1":null,"Finishes2":null,"L21_1":null,"L21_2":null,"TwentyOne1":null,"TwentyOne2":null,"Year":2019,"Season":"2019-2020","Rating1":1358.5617897762,"Rating2":1362.1189523421},{"id":3948,"Date":1571356800000,"Player1":"Andor","Player2":"Frank","Legs1":2,"Legs2":0,"Max1":null,"Max2":null,"Finishes1":null,"Finishes2":null,"L21_1":null,"L21_2":null,"TwentyOne1":null,"TwentyOne2":null,"Year":2019,"Season":"2019-2020","Rating1":1648.5779583703,"Rating2":1351.1903927903},{"id":3955,"Date":1571356800000,"Player1":"Frank","Player2":"JR","Legs1":2,"Legs2":1,"Max1":null,"Max2":null,"Finishes1":null,"Finishes2":null,"L21_1":null,"L21_2":null,"TwentyOne1":null,"TwentyOne2":null,"Year":2019,"Season":"2019-2020","Rating1":1349.9501891513,"Rating2":1027.1435737561},{"id":3960,"Date":1571356800000,"Player1":"Martin","Player2":"Frank","Legs1":2,"Legs2":0,"Max1":null,"Max2":null,"Finishes1":null,"Finishes2":null,"L21_1":null,"L21_2":null,"TwentyOne1":null,"TwentyOne2":null,"Year":2019,"Season":"2019-2020","Rating1":1224.4904638457,"Rating2":1335.5672762961}]